{"cod": "200", "message": 0.0029, "cnt": 39, "list": [{"dt": 1547175600, "main": {"temp": -0.24, "temp_min": -10.44, "temp_max": -0.24, "pressure": 956.9, "sea_level": 1034.72, "grnd_level": 956.9, "humidity": 61, "temp_kf": 10.2}, "weather": [{"id": 800, "main": "Clear", "description": "clear sky", "icon": "01d"}], "clouds": {"all": 0}, "wind": {"speed": 1.46, "deg": 258.502}, "sys": {"pod": "d"}, "dt_txt": "2019-01-11 03:00:00"}, {"dt": 1547186400, "main": {"temp": 0.81, "temp_min": -6.85, "temp_max": 0.81, "pressure": 956.54, "sea_level": 1033.14, "grnd_level": 956.54, "humidity": 59, "temp_kf": 7.65}, "weather": [{"id": 800, "main": "Clear", "description": "clear sky", "icon": "01d"}], "clouds": {"all": 0}, "wind": {"speed": 1.57, "deg": 280.504}, "sys": {"pod": "d"}, "dt_txt": "2019-01-11 06:00:00"}, {"dt": 1547197200, "main": {"temp": -10.84, "temp_min": -15.95, "temp_max": -10.84, "pressure": 957.51, "sea_level": 1035.42, "grnd_level": 957.51, "humidity": 69, "temp_kf": 5.1}, "weather": [{"id": 800, "main": "Clear", "description": "clear sky", "icon": "01n"}], "clouds": {"all": 0}, "wind": {"speed": 1.06, "deg": 260.004}, "sys": {"pod": "n"}, "dt_txt": "2019-01-11 09:00:00"}, {"dt": 1547208000, "main": {"temp": -18.49, "temp_min": -21.04, "temp_max": -18.49, "pressure": 958.26, "sea_level": 1037.27, "grnd_level": 958.26, "humidity": 54, "temp_kf": 2.55}, "weather": [{"id": 800, "main": "Clear", "description": "clear sky", "icon": "01n"}], "clouds": {"all": 0}, "wind": {"speed": 1.12, "deg": 281.501}, "sys": {"pod": "n"}, "dt_txt": "2019-01-11 12:00:00"}, {"dt": 1547218800, "main": {"temp": -22.86, "temp_min": -22.86, "temp_max": -22.86, "pressure": 958.84, "sea_level": 1038.33, "grnd_level": 958.84, "humidity": 47, "temp_kf": 0}, "weather": [{"id": 800, "main": "Clear", "description": "clear sky", "icon": "02n"}], "clouds": {"all": 8}, "wind": {"speed": 1.15, "deg": 325.503}, "sys": {"pod": "n"}, "dt_txt": "2019-01-11 15:00:00"}, {"dt": 1547229600, "main": {"temp": -23.95, "temp_min": -23.95, "temp_max": -23.95, "pressure": 959.58, "sea_level": 1039.36, "grnd_level": 959.58, "humidity": 52, "temp_kf": 0}, "weather": [{"id": 800, "main": "Clear", "description": "clear sky", "icon": "01n"}], "clouds": {"all": 0}, "wind": {"speed": 1.11, "deg": 50.5003}, "sys": {"pod": "n"}, "dt_txt": "2019-01-11 18:00:00"}, {"dt": 1547240400, "main": {"temp": -24.88, "temp_min": -24.88, "temp_max": -24.88, "pressure": 959.99, "sea_level": 1039.96, "grnd_level": 959.99, "humidity": 57, "temp_kf": 0}, "weather": [{"id": 800, "main": "Clear", "description": "clear sky", "icon": "02n"}], "clouds": {"all": 8}, "wind": {"speed": 1.06, "deg": 80.5003}, "sys": {"pod": "n"}, "dt_txt": "2019-01-11 21:00:00"}, {"dt": 1547251200, "main": {"temp": -24.61, "temp_min": -24.61, "temp_max": -24.61, "pressure": 960.32, "sea_level": 1040.51, "grnd_level": 960.32, "humidity": 55, "temp_kf": 0}, "weather": [{"id": 802, "main": "Clouds", "description": "scattered clouds", "icon": "03d"}], "clouds": {"all": 36}, "wind": {"speed": 1.11, "deg": 64.501}, "sys": {"pod": "d"}, "dt_txt": "2019-01-12 00:00:00"}, {"dt": 1547262000, "main": {"temp": -13.83, "temp_min": -13.83, "temp_max": -13.83, "pressure": 960.39, "sea_level": 1039, "grnd_level": 960.39, "humidity": 80, "temp_kf": 0}, "weather": [{"id": 800, "main": "Clear", "description": "clear sky", "icon": "01d"}], "clouds": {"all": 68}, "wind": {"speed": 1.26, "deg": 78.5017}, "snow": {"3h": 0.0075}, "sys": {"pod": "d"}, "dt_txt": "2019-01-12 03:00:00"}, {"dt": 1547272800, "main": {"temp": -12.13, "temp_min": -12.13, "temp_max": -12.13, "pressure": 959.56, "sea_level": 1037.18, "grnd_level": 959.56, "humidity": 70, "temp_kf": 0}, "weather": [{"id": 800, "main": "Clear", "description": "clear sky", "icon": "01d"}], "clouds": {"all": 36}, "wind": {"speed": 1.55, "deg": 89.5004}, "snow": {"3h": 0.01125}, "sys": {"pod": "d"}, "dt_txt": "2019-01-12 06:00:00"}, {"dt": 1547283600, "main": {"temp": -16.4, "temp_min": -16.4, "temp_max": -16.4, "pressure": 959.89, "sea_level": 1038.48, "grnd_level": 959.89, "humidity": 81, "temp_kf": 0}, "weather": [{"id": 800, "main": "Clear", "description": "clear sky", "icon": "01n"}], "clouds": {"all": 64}, "wind": {"speed": 1.22, "deg": 77.0011}, "snow": {"3h": 0.00375}, "sys": {"pod": "n"}, "dt_txt": "2019-01-12 09:00:00"}, {"dt": 1547294400, "main": {"temp": -17.77, "temp_min": -17.77, "temp_max": -17.77, "pressure": 959.52, "sea_level": 1039.02, "grnd_level": 959.52, "humidity": 61, "temp_kf": 0}, "weather": [{"id": 600, "main": "Snow", "description": "light snow", "icon": "13n"}], "clouds": {"all": 68}, "wind": {"speed": 1.51, "deg": 90.0023}, "snow": {"3h": 0.06125}, "sys": {"pod": "n"}, "dt_txt": "2019-01-12 12:00:00"}, {"dt": 1547305200, "main": {"temp": -18.09, "temp_min": -18.09, "temp_max": -18.09, "pressure": 959.69, "sea_level": 1039.45, "grnd_level": 959.69, "humidity": 73, "temp_kf": 0}, "weather": [{"id": 600, "main": "Snow", "description": "light snow", "icon": "13n"}], "clouds": {"all": 80}, "wind": {"speed": 1.12, "deg": 61.5001}, "snow": {"3h": 0.2125}, "sys": {"pod": "n"}, "dt_txt": "2019-01-12 15:00:00"}, {"dt": 1547316000, "main": {"temp": -18.46, "temp_min": -18.46, "temp_max": -18.46, "pressure": 959.65, "sea_level": 1039.67, "grnd_level": 959.65, "humidity": 65, "temp_kf": 0}, "weather": [{"id": 600, "main": "Snow", "description": "light snow", "icon": "13n"}], "clouds": {"all": 76}, "wind": {"speed": 1.16, "deg": 41.0007}, "snow": {"3h": 0.15125}, "sys": {"pod": "n"}, "dt_txt": "2019-01-12 18:00:00"}, {"dt": 1547326800, "main": {"temp": -19.5, "temp_min": -19.5, "temp_max": -19.5, "pressure": 959.46, "sea_level": 1039.84, "grnd_level": 959.46, "humidity": 70, "temp_kf": 0}, "weather": [{"id": 600, "main": "Snow", "description": "light snow", "icon": "13n"}], "clouds": {"all": 80}, "wind": {"speed": 1.06, "deg": 304.502}, "snow": {"3h": 0.0325}, "sys": {"pod": "n"}, "dt_txt": "2019-01-12 21:00:00"}, {"dt": 1547337600, "main": {"temp": -21.02, "temp_min": -21.02, "temp_max": -21.02, "pressure": 960.19, "sea_level": 1040.67, "grnd_level": 960.19, "humidity": 67, "temp_kf": 0}, "weather": [{"id": 800, "main": "Clear", "description": "clear sky", "icon": "01d"}], "clouds": {"all": 24}, "wind": {"speed": 1.14, "deg": 280.502}, "snow": {"3h": 0.0175}, "sys": {"pod": "d"}, "dt_txt": "2019-01-13 00:00:00"}, {"dt": 1547348400, "main": {"temp": -13.88, "temp_min": -13.88, "temp_max": -13.88, "pressure": 960.25, "sea_level": 1039.32, "grnd_level": 960.25, "humidity": 66, "temp_kf": 0}, "weather": [{"id": 800, "main": "Clear", "description": "clear sky", "icon": "01d"}], "clouds": {"all": 0}, "wind": {"speed": 1.58, "deg": 297.002}, "snow": {}, "sys": {"pod": "d"}, "dt_txt": "2019-01-13 03:00:00"}, {"dt": 1547359200, "main": {"temp": -10.32, "temp_min": -10.32, "temp_max": -10.32, "pressure": 959.86, "sea_level": 1037.77, "grnd_level": 959.86, "humidity": 66, "temp_kf": 0}, "weather": [{"id": 800, "main": "Clear", "description": "clear sky", "icon": "01d"}], "clouds": {"all": 12}, "wind": {"speed": 1.59, "deg": 319.001}, "snow": {"3h": 0.0025}, "sys": {"pod": "d"}, "dt_txt": "2019-01-13 06:00:00"}, {"dt": 1547370000, "main": {"temp": -16.06, "temp_min": -16.06, "temp_max": -16.06, "pressure": 960.03, "sea_level": 1038.92, "grnd_level": 960.03, "humidity": 70, "temp_kf": 0}, "weather": [{"id": 800, "main": "Clear", "description": "clear sky", "icon": "01n"}], "clouds": {"all": 48}, "wind": {"speed": 1.49, "deg": 275.5}, "snow": {"3h": 0.01}, "sys": {"pod": "n"}, "dt_txt": "2019-01-13 09:00:00"}, {"dt": 1547380800, "main": {"temp": -17.43, "temp_min": -17.43, "temp_max": -17.43, "pressure": 959.81, "sea_level": 1039.3, "grnd_level": 959.81, "humidity": 59, "temp_kf": 0}, "weather": [{"id": 600, "main": "Snow", "description": "light snow", "icon": "13n"}], "clouds": {"all": 56}, "wind": {"speed": 1.45, "deg": 266.001}, "snow": {"3h": 0.0325}, "sys": {"pod": "n"}, "dt_txt": "2019-01-13 12:00:00"}, {"dt": 1547391600, "main": {"temp": -19.37, "temp_min": -19.37, "temp_max": -19.37, "pressure": 959.1, "sea_level": 1038.84, "grnd_level": 959.1, "humidity": 58, "temp_kf": 0}, "weather": [{"id": 800, "main": "Clear", "description": "clear sky", "icon": "01n"}], "clouds": {"all": 64}, "wind": {"speed": 1.13, "deg": 245}, "snow": {"3h": 0.0075000000000001}, "sys": {"pod": "n"}, "dt_txt": "2019-01-13 15:00:00"}, {"dt": 1547402400, "main": {"temp": -19.96, "temp_min": -19.96, "temp_max": -19.96, "pressure": 957.84, "sea_level": 1037.74, "grnd_level": 957.84, "humidity": 61, "temp_kf": 0}, "weather": [{"id": 800, "main": "Clear", "description": "clear sky", "icon": "01n"}], "clouds": {"all": 64}, "wind": {"speed": 1.07, "deg": 238.501}, "snow": {"3h": 0.0175}, "sys": {"pod": "n"}, "dt_txt": "2019-01-13 18:00:00"}, {"dt": 1547413200, "main": {"temp": -20.34, "temp_min": -20.34, "temp_max": -20.34, "pressure": 956.73, "sea_level": 1036.52, "grnd_level": 956.73, "humidity": 76, "temp_kf": 0}, "weather": [{"id": 600, "main": "Snow", "description": "light snow", "icon": "13n"}], "clouds": {"all": 76}, "wind": {"speed": 0.48, "deg": 336.002}, "snow": {"3h": 0.06}, "sys": {"pod": "n"}, "dt_txt": "2019-01-13 21:00:00"}, {"dt": 1547424000, "main": {"temp": -20.78, "temp_min": -20.78, "temp_max": -20.78, "pressure": 956.49, "sea_level": 1036.22, "grnd_level": 956.49, "humidity": 78, "temp_kf": 0}, "weather": [{"id": 600, "main": "Snow", "description": "light snow", "icon": "13d"}], "clouds": {"all": 76}, "wind": {"speed": 1.01, "deg": 353.505}, "snow": {"3h": 0.0525}, "sys": {"pod": "d"}, "dt_txt": "2019-01-14 00:00:00"}, {"dt": 1547434800, "main": {"temp": -16.35, "temp_min": -16.35, "temp_max": -16.35, "pressure": 955.81, "sea_level": 1034.6, "grnd_level": 955.81, "humidity": 72, "temp_kf": 0}, "weather": [{"id": 600, "main": "Snow", "description": "light snow", "icon": "13d"}], "clouds": {"all": 68}, "wind": {"speed": 1.61, "deg": 329.5}, "snow": {"3h": 0.045}, "sys": {"pod": "d"}, "dt_txt": "2019-01-14 03:00:00"}, {"dt": 1547445600, "main": {"temp": -14.52, "temp_min": -14.52, "temp_max": -14.52, "pressure": 955.44, "sea_level": 1033.78, "grnd_level": 955.44, "humidity": 69, "temp_kf": 0}, "weather": [{"id": 600, "main": "Snow", "description": "light snow", "icon": "13d"}], "clouds": {"all": 64}, "wind": {"speed": 2.16, "deg": 353.007}, "snow": {"3h": 0.1025}, "sys": {"pod": "d"}, "dt_txt": "2019-01-14 06:00:00"}, {"dt": 1547456400, "main": {"temp": -15.39, "temp_min": -15.39, "temp_max": -15.39, "pressure": 956.62, "sea_level": 1035.62, "grnd_level": 956.62, "humidity": 66, "temp_kf": 0}, "weather": [{"id": 600, "main": "Snow", "description": "light snow", "icon": "13n"}], "clouds": {"all": 56}, "wind": {"speed": 2.51, "deg": 358.503}, "snow": {"3h": 0.2225}, "sys": {"pod": "n"}, "dt_txt": "2019-01-14 09:00:00"}, {"dt": 1547467200, "main": {"temp": -16.82, "temp_min": -16.82, "temp_max": -16.82, "pressure": 957.99, "sea_level": 1037.39, "grnd_level": 957.99, "humidity": 56, "temp_kf": 0}, "weather": [{"id": 600, "main": "Snow", "description": "light snow", "icon": "13n"}], "clouds": {"all": 56}, "wind": {"speed": 3.12, "deg": 347.003}, "snow": {"3h": 0.1525}, "sys": {"pod": "n"}, "dt_txt": "2019-01-14 12:00:00"}, {"dt": 1547478000, "main": {"temp": -17.7, "temp_min": -17.7, "temp_max": -17.7, "pressure": 958.35, "sea_level": 1038.07, "grnd_level": 958.35, "humidity": 50, "temp_kf": 0}, "weather": [{"id": 600, "main": "Snow", "description": "light snow", "icon": "13n"}], "clouds": {"all": 48}, "wind": {"speed": 3.32, "deg": 337.5}, "snow": {"3h": 0.0725}, "sys": {"pod": "n"}, "dt_txt": "2019-01-14 15:00:00"}, {"dt": 1547488800, "main": {"temp": -17.91, "temp_min": -17.91, "temp_max": -17.91, "pressure": 958.56, "sea_level": 1038.51, "grnd_level": 958.56, "humidity": 51, "temp_kf": 0}, "weather": [{"id": 600, "main": "Snow", "description": "light snow", "icon": "13n"}], "clouds": {"all": 56}, "wind": {"speed": 3.56, "deg": 332.002}, "snow": {"3h": 0.0425}, "sys": {"pod": "n"}, "dt_txt": "2019-01-14 18:00:00"}, {"dt": 1547499600, "main": {"temp": -18.72, "temp_min": -18.72, "temp_max": -18.72, "pressure": 958.22, "sea_level": 1038.31, "grnd_level": 958.22, "humidity": 55, "temp_kf": 0}, "weather": [{"id": 800, "main": "Clear", "description": "clear sky", "icon": "01n"}], "clouds": {"all": 48}, "wind": {"speed": 3.61, "deg": 326.001}, "snow": {"3h": 0.0175}, "sys": {"pod": "n"}, "dt_txt": "2019-01-14 21:00:00"}, {"dt": 1547510400, "main": {"temp": -20.58, "temp_min": -20.58, "temp_max": -20.58, "pressure": 958.44, "sea_level": 1038.8, "grnd_level": 958.44, "humidity": 52, "temp_kf": 0}, "weather": [{"id": 800, "main": "Clear", "description": "clear sky", "icon": "01d"}], "clouds": {"all": 8}, "wind": {"speed": 3.32, "deg": 321.002}, "snow": {"3h": 0.0024999999999999}, "sys": {"pod": "d"}, "dt_txt": "2019-01-15 00:00:00"}, {"dt": 1547521200, "main": {"temp": -18.72, "temp_min": -18.72, "temp_max": -18.72, "pressure": 958.32, "sea_level": 1037.81, "grnd_level": 958.32, "humidity": 44, "temp_kf": 0}, "weather": [{"id": 800, "main": "Clear", "description": "clear sky", "icon": "01d"}], "clouds": {"all": 0}, "wind": {"speed": 3.16, "deg": 321.501}, "snow": {}, "sys": {"pod": "d"}, "dt_txt": "2019-01-15 03:00:00"}, {"dt": 1547532000, "main": {"temp": -17.82, "temp_min": -17.82, "temp_max": -17.82, "pressure": 957.75, "sea_level": 1036.6, "grnd_level": 957.75, "humidity": 41, "temp_kf": 0}, "weather": [{"id": 800, "main": "Clear", "description": "clear sky", "icon": "01d"}], "clouds": {"all": 0}, "wind": {"speed": 3.07, "deg": 322.5}, "snow": {}, "sys": {"pod": "d"}, "dt_txt": "2019-01-15 06:00:00"}, {"dt": 1547542800, "main": {"temp": -20.54, "temp_min": -20.54, "temp_max": -20.54, "pressure": 958.59, "sea_level": 1038.24, "grnd_level": 958.59, "humidity": 51, "temp_kf": 0}, "weather": [{"id": 800, "main": "Clear", "description": "clear sky", "icon": "01n"}], "clouds": {"all": 0}, "wind": {"speed": 2.77, "deg": 322.5}, "snow": {}, "sys": {"pod": "n"}, "dt_txt": "2019-01-15 09:00:00"}, {"dt": 1547553600, "main": {"temp": -22.91, "temp_min": -22.91, "temp_max": -22.91, "pressure": 959.63, "sea_level": 1040.09, "grnd_level": 959.63, "humidity": 32, "temp_kf": 0}, "weather": [{"id": 800, "main": "Clear", "description": "clear sky", "icon": "01n"}], "clouds": {"all": 0}, "wind": {"speed": 2.48, "deg": 325.001}, "snow": {}, "sys": {"pod": "n"}, "dt_txt": "2019-01-15 12:00:00"}, {"dt": 1547564400, "main": {"temp": -24.74, "temp_min": -24.74, "temp_max": -24.74, "pressure": 960.49, "sea_level": 1041.56, "grnd_level": 960.49, "humidity": 56, "temp_kf": 0}, "weather": [{"id": 800, "main": "Clear", "description": "clear sky", "icon": "01n"}], "clouds": {"all": 0}, "wind": {"speed": 2.32, "deg": 319.5}, "snow": {}, "sys": {"pod": "n"}, "dt_txt": "2019-01-15 15:00:00"}, {"dt": 1547575200, "main": {"temp": -25.7, "temp_min": -25.7, "temp_max": -25.7, "pressure": 960.86, "sea_level": 1042.37, "grnd_level": 960.86, "humidity": 41, "temp_kf": 0}, "weather": [{"id": 800, "main": "Clear", "description": "clear sky", "icon": "01n"}], "clouds": {"all": 0}, "wind": {"speed": 2.28, "deg": 315.502}, "snow": {}, "sys": {"pod": "n"}, "dt_txt": "2019-01-15 18:00:00"}, {"dt": 1547586000, "main": {"temp": -25.4, "temp_min": -25.4, "temp_max": -25.4, "pressure": 960.74, "sea_level": 1042.43, "grnd_level": 960.74, "humidity": 40, "temp_kf": 0}, "weather": [{"id": 800, "main": "Clear", "description": "clear sky", "icon": "01n"}], "clouds": {"all": 0}, "wind": {"speed": 2.59, "deg": 310.003}, "snow": {}, "sys": {"pod": "n"}, "dt_txt": "2019-01-15 21:00:00"}], "city": {"id": 2038665, "name": "Alihe", "coord": {"lat": 50.5723, "lon": 123.7337}, "country": "CN", "population": 61582}}