{"cod": "200", "message": 0.0032, "cnt": 39, "list": [{"dt": 1547175600, "main": {"temp": 24.17, "temp_min": 24.17, "temp_max": 25.44, "pressure": 1024.17, "sea_level": 1027.79, "grnd_level": 1024.17, "humidity": 79, "temp_kf": -1.27}, "weather": [{"id": 804, "main": "Clouds", "description": "overcast clouds", "icon": "04n"}], "clouds": {"all": 92}, "wind": {"speed": 2.66, "deg": 98.0024}, "sys": {"pod": "n"}, "dt_txt": "2019-01-11 03:00:00"}, {"dt": 1547186400, "main": {"temp": 24.31, "temp_min": 24.31, "temp_max": 25.26, "pressure": 1023.33, "sea_level": 1026.94, "grnd_level": 1023.33, "humidity": 79, "temp_kf": -0.95}, "weather": [{"id": 500, "main": "Rain", "description": "light rain", "icon": "10n"}], "clouds": {"all": 92}, "wind": {"speed": 2.37, "deg": 93.5035}, "rain": {"3h": 0.01}, "sys": {"pod": "n"}, "dt_txt": "2019-01-11 06:00:00"}, {"dt": 1547197200, "main": {"temp": 24.33, "temp_min": 24.33, "temp_max": 24.96, "pressure": 1023.25, "sea_level": 1026.95, "grnd_level": 1023.25, "humidity": 81, "temp_kf": -0.63}, "weather": [{"id": 804, "main": "Clouds", "description": "overcast clouds", "icon": "04n"}], "clouds": {"all": 92}, "wind": {"speed": 2.46, "deg": 92.504}, "rain": {}, "sys": {"pod": "n"}, "dt_txt": "2019-01-11 09:00:00"}, {"dt": 1547208000, "main": {"temp": 25.07, "temp_min": 25.07, "temp_max": 25.39, "pressure": 1025.3, "sea_level": 1028.88, "grnd_level": 1025.3, "humidity": 80, "temp_kf": -0.32}, "weather": [{"id": 500, "main": "Rain", "description": "light rain", "icon": "10d"}], "clouds": {"all": 92}, "wind": {"speed": 2.42, "deg": 92.5009}, "rain": {"3h": 0.005}, "sys": {"pod": "d"}, "dt_txt": "2019-01-11 12:00:00"}, {"dt": 1547218800, "main": {"temp": 27.65, "temp_min": 27.65, "temp_max": 27.65, "pressure": 1025.47, "sea_level": 1029.25, "grnd_level": 1025.47, "humidity": 70, "temp_kf": 0}, "weather": [{"id": 803, "main": "Clouds", "description": "broken clouds", "icon": "04d"}], "clouds": {"all": 80}, "wind": {"speed": 2.8, "deg": 97.0031}, "rain": {}, "sys": {"pod": "d"}, "dt_txt": "2019-01-11 15:00:00"}, {"dt": 1547229600, "main": {"temp": 27.7, "temp_min": 27.7, "temp_max": 27.7, "pressure": 1023.62, "sea_level": 1027.28, "grnd_level": 1023.62, "humidity": 69, "temp_kf": 0}, "weather": [{"id": 804, "main": "Clouds", "description": "overcast clouds", "icon": "04d"}], "clouds": {"all": 88}, "wind": {"speed": 3.21, "deg": 96.5003}, "rain": {}, "sys": {"pod": "d"}, "dt_txt": "2019-01-11 18:00:00"}, {"dt": 1547240400, "main": {"temp": 26.77, "temp_min": 26.77, "temp_max": 26.77, "pressure": 1023.14, "sea_level": 1026.87, "grnd_level": 1023.14, "humidity": 71, "temp_kf": 0}, "weather": [{"id": 804, "main": "Clouds", "description": "overcast clouds", "icon": "04d"}], "clouds": {"all": 88}, "wind": {"speed": 3.41, "deg": 91.5003}, "rain": {}, "sys": {"pod": "d"}, "dt_txt": "2019-01-11 21:00:00"}, {"dt": 1547251200, "main": {"temp": 25.84, "temp_min": 25.84, "temp_max": 25.84, "pressure": 1024.52, "sea_level": 1028.14, "grnd_level": 1024.52, "humidity": 77, "temp_kf": 0}, "weather": [{"id": 803, "main": "Clouds", "description": "broken clouds", "icon": "04n"}], "clouds": {"all": 68}, "wind": {"speed": 3.31, "deg": 86.001}, "rain": {}, "sys": {"pod": "n"}, "dt_txt": "2019-01-12 00:00:00"}, {"dt": 1547262000, "main": {"temp": 25.2, "temp_min": 25.2, "temp_max": 25.2, "pressure": 1024.84, "sea_level": 1028.5, "grnd_level": 1024.84, "humidity": 82, "temp_kf": 0}, "weather": [{"id": 500, "main": "Rain", "description": "light rain", "icon": "10n"}], "clouds": {"all": 88}, "wind": {"speed": 3.11, "deg": 83.0017}, "rain": {"3h": 0.005}, "sys": {"pod": "n"}, "dt_txt": "2019-01-12 03:00:00"}, {"dt": 1547272800, "main": {"temp": 24.85, "temp_min": 24.85, "temp_max": 24.85, "pressure": 1023.43, "sea_level": 1027.09, "grnd_level": 1023.43, "humidity": 84, "temp_kf": 0}, "weather": [{"id": 500, "main": "Rain", "description": "light rain", "icon": "10n"}], "clouds": {"all": 92}, "wind": {"speed": 2.8, "deg": 80.0004}, "rain": {"3h": 0.02}, "sys": {"pod": "n"}, "dt_txt": "2019-01-12 06:00:00"}, {"dt": 1547283600, "main": {"temp": 24.93, "temp_min": 24.93, "temp_max": 24.93, "pressure": 1023.2, "sea_level": 1026.85, "grnd_level": 1023.2, "humidity": 82, "temp_kf": 0}, "weather": [{"id": 500, "main": "Rain", "description": "light rain", "icon": "10n"}], "clouds": {"all": 88}, "wind": {"speed": 2.62, "deg": 77.5011}, "rain": {"3h": 0.06}, "sys": {"pod": "n"}, "dt_txt": "2019-01-12 09:00:00"}, {"dt": 1547294400, "main": {"temp": 25.59, "temp_min": 25.59, "temp_max": 25.59, "pressure": 1025.18, "sea_level": 1028.84, "grnd_level": 1025.18, "humidity": 79, "temp_kf": 0}, "weather": [{"id": 500, "main": "Rain", "description": "light rain", "icon": "10d"}], "clouds": {"all": 92}, "wind": {"speed": 2.56, "deg": 76.5023}, "rain": {"3h": 0.02}, "sys": {"pod": "d"}, "dt_txt": "2019-01-12 12:00:00"}, {"dt": 1547305200, "main": {"temp": 27.56, "temp_min": 27.56, "temp_max": 27.56, "pressure": 1025.92, "sea_level": 1029.52, "grnd_level": 1025.92, "humidity": 69, "temp_kf": 0}, "weather": [{"id": 803, "main": "Clouds", "description": "broken clouds", "icon": "04d"}], "clouds": {"all": 80}, "wind": {"speed": 2.97, "deg": 79.5001}, "rain": {}, "sys": {"pod": "d"}, "dt_txt": "2019-01-12 15:00:00"}, {"dt": 1547316000, "main": {"temp": 28.34, "temp_min": 28.34, "temp_max": 28.34, "pressure": 1023.69, "sea_level": 1027.51, "grnd_level": 1023.69, "humidity": 65, "temp_kf": 0}, "weather": [{"id": 803, "main": "Clouds", "description": "broken clouds", "icon": "04d"}], "clouds": {"all": 68}, "wind": {"speed": 2.96, "deg": 78.0007}, "rain": {}, "sys": {"pod": "d"}, "dt_txt": "2019-01-12 18:00:00"}, {"dt": 1547326800, "main": {"temp": 27.33, "temp_min": 27.33, "temp_max": 27.33, "pressure": 1022.93, "sea_level": 1026.67, "grnd_level": 1022.93, "humidity": 68, "temp_kf": 0}, "weather": [{"id": 800, "main": "Clear", "description": "clear sky", "icon": "01d"}], "clouds": {"all": 0}, "wind": {"speed": 3.26, "deg": 70.502}, "rain": {}, "sys": {"pod": "d"}, "dt_txt": "2019-01-12 21:00:00"}, {"dt": 1547337600, "main": {"temp": 25.24, "temp_min": 25.24, "temp_max": 25.24, "pressure": 1024.39, "sea_level": 1028.1, "grnd_level": 1024.39, "humidity": 77, "temp_kf": 0}, "weather": [{"id": 800, "main": "Clear", "description": "clear sky", "icon": "01n"}], "clouds": {"all": 0}, "wind": {"speed": 2.87, "deg": 65.0016}, "rain": {}, "sys": {"pod": "n"}, "dt_txt": "2019-01-13 00:00:00"}, {"dt": 1547348400, "main": {"temp": 24.53, "temp_min": 24.53, "temp_max": 24.53, "pressure": 1024.69, "sea_level": 1028.42, "grnd_level": 1024.69, "humidity": 82, "temp_kf": 0}, "weather": [{"id": 800, "main": "Clear", "description": "clear sky", "icon": "01n"}], "clouds": {"all": 0}, "wind": {"speed": 2.71, "deg": 64.002}, "rain": {}, "sys": {"pod": "n"}, "dt_txt": "2019-01-13 03:00:00"}, {"dt": 1547359200, "main": {"temp": 24.34, "temp_min": 24.34, "temp_max": 24.34, "pressure": 1023.4, "sea_level": 1027.15, "grnd_level": 1023.4, "humidity": 86, "temp_kf": 0}, "weather": [{"id": 500, "main": "Rain", "description": "light rain", "icon": "10n"}], "clouds": {"all": 80}, "wind": {"speed": 2.39, "deg": 57.0013}, "rain": {"3h": 0.02}, "sys": {"pod": "n"}, "dt_txt": "2019-01-13 06:00:00"}, {"dt": 1547370000, "main": {"temp": 24.59, "temp_min": 24.59, "temp_max": 24.59, "pressure": 1022.94, "sea_level": 1026.72, "grnd_level": 1022.94, "humidity": 84, "temp_kf": 0}, "weather": [{"id": 500, "main": "Rain", "description": "light rain", "icon": "10n"}], "clouds": {"all": 88}, "wind": {"speed": 2.49, "deg": 58}, "rain": {"3h": 0.04}, "sys": {"pod": "n"}, "dt_txt": "2019-01-13 09:00:00"}, {"dt": 1547380800, "main": {"temp": 25.47, "temp_min": 25.47, "temp_max": 25.47, "pressure": 1024.9, "sea_level": 1028.68, "grnd_level": 1024.9, "humidity": 79, "temp_kf": 0}, "weather": [{"id": 500, "main": "Rain", "description": "light rain", "icon": "10d"}], "clouds": {"all": 92}, "wind": {"speed": 2.7, "deg": 66.001}, "rain": {"3h": 0.09}, "sys": {"pod": "d"}, "dt_txt": "2019-01-13 12:00:00"}, {"dt": 1547391600, "main": {"temp": 27.23, "temp_min": 27.23, "temp_max": 27.23, "pressure": 1025.64, "sea_level": 1029.28, "grnd_level": 1025.64, "humidity": 71, "temp_kf": 0}, "weather": [{"id": 803, "main": "Clouds", "description": "broken clouds", "icon": "04d"}], "clouds": {"all": 80}, "wind": {"speed": 3.18, "deg": 73.0005}, "rain": {}, "sys": {"pod": "d"}, "dt_txt": "2019-01-13 15:00:00"}, {"dt": 1547402400, "main": {"temp": 27.55, "temp_min": 27.55, "temp_max": 27.55, "pressure": 1023.59, "sea_level": 1027.28, "grnd_level": 1023.59, "humidity": 68, "temp_kf": 0}, "weather": [{"id": 804, "main": "Clouds", "description": "overcast clouds", "icon": "04d"}], "clouds": {"all": 88}, "wind": {"speed": 3.14, "deg": 74.5008}, "rain": {}, "sys": {"pod": "d"}, "dt_txt": "2019-01-13 18:00:00"}, {"dt": 1547413200, "main": {"temp": 26.81, "temp_min": 26.81, "temp_max": 26.81, "pressure": 1022.96, "sea_level": 1026.55, "grnd_level": 1022.96, "humidity": 71, "temp_kf": 0}, "weather": [{"id": 801, "main": "Clouds", "description": "few clouds", "icon": "02d"}], "clouds": {"all": 20}, "wind": {"speed": 3.03, "deg": 68.0025}, "rain": {}, "sys": {"pod": "d"}, "dt_txt": "2019-01-13 21:00:00"}, {"dt": 1547424000, "main": {"temp": 24.98, "temp_min": 24.98, "temp_max": 24.98, "pressure": 1024.33, "sea_level": 1027.95, "grnd_level": 1024.33, "humidity": 77, "temp_kf": 0}, "weather": [{"id": 800, "main": "Clear", "description": "clear sky", "icon": "01n"}], "clouds": {"all": 0}, "wind": {"speed": 2.61, "deg": 63.0049}, "rain": {}, "sys": {"pod": "n"}, "dt_txt": "2019-01-14 00:00:00"}, {"dt": 1547434800, "main": {"temp": 24.15, "temp_min": 24.15, "temp_max": 24.15, "pressure": 1024.8, "sea_level": 1028.48, "grnd_level": 1024.8, "humidity": 81, "temp_kf": 0}, "weather": [{"id": 500, "main": "Rain", "description": "light rain", "icon": "10n"}], "clouds": {"all": 0}, "wind": {"speed": 2.31, "deg": 63.0002}, "rain": {"3h": 0.01}, "sys": {"pod": "n"}, "dt_txt": "2019-01-14 03:00:00"}, {"dt": 1547445600, "main": {"temp": 23.39, "temp_min": 23.39, "temp_max": 23.39, "pressure": 1023.7, "sea_level": 1027.37, "grnd_level": 1023.7, "humidity": 86, "temp_kf": 0}, "weather": [{"id": 500, "main": "Rain", "description": "light rain", "icon": "10n"}], "clouds": {"all": 12}, "wind": {"speed": 2.01, "deg": 62.507}, "rain": {"3h": 0.01}, "sys": {"pod": "n"}, "dt_txt": "2019-01-14 06:00:00"}, {"dt": 1547456400, "main": {"temp": 23.12, "temp_min": 23.12, "temp_max": 23.12, "pressure": 1023.25, "sea_level": 1026.99, "grnd_level": 1023.25, "humidity": 87, "temp_kf": 0}, "weather": [{"id": 801, "main": "Clouds", "description": "few clouds", "icon": "02n"}], "clouds": {"all": 24}, "wind": {"speed": 1.91, "deg": 64.503}, "rain": {}, "sys": {"pod": "n"}, "dt_txt": "2019-01-14 09:00:00"}, {"dt": 1547467200, "main": {"temp": 24.99, "temp_min": 24.99, "temp_max": 24.99, "pressure": 1025.02, "sea_level": 1028.67, "grnd_level": 1025.02, "humidity": 80, "temp_kf": 0}, "weather": [{"id": 802, "main": "Clouds", "description": "scattered clouds", "icon": "03d"}], "clouds": {"all": 32}, "wind": {"speed": 2.07, "deg": 70.5034}, "rain": {}, "sys": {"pod": "d"}, "dt_txt": "2019-01-14 12:00:00"}, {"dt": 1547478000, "main": {"temp": 28.26, "temp_min": 28.26, "temp_max": 28.26, "pressure": 1025.47, "sea_level": 1029.24, "grnd_level": 1025.47, "humidity": 65, "temp_kf": 0}, "weather": [{"id": 803, "main": "Clouds", "description": "broken clouds", "icon": "04d"}], "clouds": {"all": 56}, "wind": {"speed": 2.67, "deg": 72.5004}, "rain": {}, "sys": {"pod": "d"}, "dt_txt": "2019-01-14 15:00:00"}, {"dt": 1547488800, "main": {"temp": 28.45, "temp_min": 28.45, "temp_max": 28.45, "pressure": 1023.58, "sea_level": 1027.28, "grnd_level": 1023.58, "humidity": 64, "temp_kf": 0}, "weather": [{"id": 802, "main": "Clouds", "description": "scattered clouds", "icon": "03d"}], "clouds": {"all": 48}, "wind": {"speed": 3.16, "deg": 79.0022}, "rain": {}, "sys": {"pod": "d"}, "dt_txt": "2019-01-14 18:00:00"}, {"dt": 1547499600, "main": {"temp": 27.24, "temp_min": 27.24, "temp_max": 27.24, "pressure": 1022.91, "sea_level": 1026.55, "grnd_level": 1022.91, "humidity": 68, "temp_kf": 0}, "weather": [{"id": 800, "main": "Clear", "description": "clear sky", "icon": "01d"}], "clouds": {"all": 0}, "wind": {"speed": 3.06, "deg": 76.5007}, "rain": {}, "sys": {"pod": "d"}, "dt_txt": "2019-01-14 21:00:00"}, {"dt": 1547510400, "main": {"temp": 24.97, "temp_min": 24.97, "temp_max": 24.97, "pressure": 1024.1, "sea_level": 1027.66, "grnd_level": 1024.1, "humidity": 80, "temp_kf": 0}, "weather": [{"id": 800, "main": "Clear", "description": "clear sky", "icon": "01n"}], "clouds": {"all": 0}, "wind": {"speed": 2.67, "deg": 74.5016}, "rain": {}, "sys": {"pod": "n"}, "dt_txt": "2019-01-15 00:00:00"}, {"dt": 1547521200, "main": {"temp": 24.78, "temp_min": 24.78, "temp_max": 24.78, "pressure": 1024.55, "sea_level": 1028.25, "grnd_level": 1024.55, "humidity": 82, "temp_kf": 0}, "weather": [{"id": 804, "main": "Clouds", "description": "overcast clouds", "icon": "04n"}], "clouds": {"all": 88}, "wind": {"speed": 2.41, "deg": 74.5009}, "rain": {}, "sys": {"pod": "n"}, "dt_txt": "2019-01-15 03:00:00"}, {"dt": 1547532000, "main": {"temp": 24.94, "temp_min": 24.94, "temp_max": 24.94, "pressure": 1023.16, "sea_level": 1026.95, "grnd_level": 1023.16, "humidity": 82, "temp_kf": 0}, "weather": [{"id": 803, "main": "Clouds", "description": "broken clouds", "icon": "04n"}], "clouds": {"all": 68}, "wind": {"speed": 2.37, "deg": 69.5004}, "rain": {}, "sys": {"pod": "n"}, "dt_txt": "2019-01-15 06:00:00"}, {"dt": 1547542800, "main": {"temp": 24.91, "temp_min": 24.91, "temp_max": 24.91, "pressure": 1022.96, "sea_level": 1026.69, "grnd_level": 1022.96, "humidity": 82, "temp_kf": 0}, "weather": [{"id": 804, "main": "Clouds", "description": "overcast clouds", "icon": "04n"}], "clouds": {"all": 88}, "wind": {"speed": 2.32, "deg": 66.0005}, "rain": {}, "sys": {"pod": "n"}, "dt_txt": "2019-01-15 09:00:00"}, {"dt": 1547553600, "main": {"temp": 25.44, "temp_min": 25.44, "temp_max": 25.44, "pressure": 1024.8, "sea_level": 1028.46, "grnd_level": 1024.8, "humidity": 79, "temp_kf": 0}, "weather": [{"id": 804, "main": "Clouds", "description": "overcast clouds", "icon": "04d"}], "clouds": {"all": 92}, "wind": {"speed": 2.38, "deg": 73.5005}, "rain": {}, "sys": {"pod": "d"}, "dt_txt": "2019-01-15 12:00:00"}, {"dt": 1547564400, "main": {"temp": 26.36, "temp_min": 26.36, "temp_max": 26.36, "pressure": 1025.74, "sea_level": 1029.44, "grnd_level": 1025.74, "humidity": 78, "temp_kf": 0}, "weather": [{"id": 500, "main": "Rain", "description": "light rain", "icon": "10d"}], "clouds": {"all": 92}, "wind": {"speed": 2.77, "deg": 87.5004}, "rain": {"3h": 0.06}, "sys": {"pod": "d"}, "dt_txt": "2019-01-15 15:00:00"}, {"dt": 1547575200, "main": {"temp": 26.45, "temp_min": 26.45, "temp_max": 26.45, "pressure": 1023.92, "sea_level": 1027.58, "grnd_level": 1023.92, "humidity": 77, "temp_kf": 0}, "weather": [{"id": 500, "main": "Rain", "description": "light rain", "icon": "10d"}], "clouds": {"all": 92}, "wind": {"speed": 2.73, "deg": 86.5015}, "rain": {"3h": 0.02}, "sys": {"pod": "d"}, "dt_txt": "2019-01-15 18:00:00"}, {"dt": 1547586000, "main": {"temp": 26.28, "temp_min": 26.28, "temp_max": 26.28, "pressure": 1023, "sea_level": 1026.71, "grnd_level": 1023, "humidity": 77, "temp_kf": 0}, "weather": [{"id": 804, "main": "Clouds", "description": "overcast clouds", "icon": "04d"}], "clouds": {"all": 92}, "wind": {"speed": 3.04, "deg": 85.0033}, "rain": {}, "sys": {"pod": "d"}, "dt_txt": "2019-01-15 21:00:00"}], "city": {"id": 3573739, "name": "Esperance", "coord": {"lat": 10.2447, "lon": -61.4506}, "country": "TT", "population": 56380}}