{"cod": "200", "message": 0.0052, "cnt": 39, "list": [{"dt": 1547175600, "main": {"temp": 21.25, "temp_min": 21.25, "temp_max": 21.41, "pressure": 990.94, "sea_level": 1023.37, "grnd_level": 990.94, "humidity": 92, "temp_kf": -0.16}, "weather": [{"id": 500, "main": "Rain", "description": "light rain", "icon": "10n"}], "clouds": {"all": 24}, "wind": {"speed": 3.91, "deg": 238.502}, "rain": {"3h": 0.75}, "sys": {"pod": "n"}, "dt_txt": "2019-01-11 03:00:00"}, {"dt": 1547186400, "main": {"temp": 21.04, "temp_min": 21.04, "temp_max": 21.16, "pressure": 992.05, "sea_level": 1024.43, "grnd_level": 992.05, "humidity": 93, "temp_kf": -0.12}, "weather": [{"id": 500, "main": "Rain", "description": "light rain", "icon": "10n"}], "clouds": {"all": 24}, "wind": {"speed": 3.47, "deg": 219.004}, "rain": {"3h": 0.735}, "sys": {"pod": "n"}, "dt_txt": "2019-01-11 06:00:00"}, {"dt": 1547197200, "main": {"temp": 26.98, "temp_min": 26.98, "temp_max": 27.06, "pressure": 993.83, "sea_level": 1026.14, "grnd_level": 993.83, "humidity": 72, "temp_kf": -0.08}, "weather": [{"id": 800, "main": "Clear", "description": "clear sky", "icon": "02d"}], "clouds": {"all": 8}, "wind": {"speed": 3.11, "deg": 222.504}, "rain": {}, "sys": {"pod": "d"}, "dt_txt": "2019-01-11 09:00:00"}, {"dt": 1547208000, "main": {"temp": 32.17, "temp_min": 32.17, "temp_max": 32.21, "pressure": 992.31, "sea_level": 1024.26, "grnd_level": 992.31, "humidity": 62, "temp_kf": -0.04}, "weather": [{"id": 800, "main": "Clear", "description": "clear sky", "icon": "01d"}], "clouds": {"all": 0}, "wind": {"speed": 2.57, "deg": 236.001}, "rain": {}, "sys": {"pod": "d"}, "dt_txt": "2019-01-11 12:00:00"}, {"dt": 1547218800, "main": {"temp": 33.72, "temp_min": 33.72, "temp_max": 33.72, "pressure": 989.4, "sea_level": 1021.14, "grnd_level": 989.4, "humidity": 51, "temp_kf": 0}, "weather": [{"id": 802, "main": "Clouds", "description": "scattered clouds", "icon": "03d"}], "clouds": {"all": 32}, "wind": {"speed": 2, "deg": 356.503}, "rain": {}, "sys": {"pod": "d"}, "dt_txt": "2019-01-11 15:00:00"}, {"dt": 1547229600, "main": {"temp": 32.23, "temp_min": 32.23, "temp_max": 32.23, "pressure": 989.73, "sea_level": 1021.49, "grnd_level": 989.73, "humidity": 44, "temp_kf": 0}, "weather": [{"id": 802, "main": "Clouds", "description": "scattered clouds", "icon": "03d"}], "clouds": {"all": 48}, "wind": {"speed": 1.36, "deg": 27.0003}, "rain": {}, "sys": {"pod": "d"}, "dt_txt": "2019-01-11 18:00:00"}, {"dt": 1547240400, "main": {"temp": 25.45, "temp_min": 25.45, "temp_max": 25.45, "pressure": 992.25, "sea_level": 1024.44, "grnd_level": 992.25, "humidity": 69, "temp_kf": 0}, "weather": [{"id": 801, "main": "Clouds", "description": "few clouds", "icon": "02n"}], "clouds": {"all": 20}, "wind": {"speed": 2.66, "deg": 129.5}, "rain": {}, "sys": {"pod": "n"}, "dt_txt": "2019-01-11 21:00:00"}, {"dt": 1547251200, "main": {"temp": 23.29, "temp_min": 23.29, "temp_max": 23.29, "pressure": 992.25, "sea_level": 1024.46, "grnd_level": 992.25, "humidity": 78, "temp_kf": 0}, "weather": [{"id": 801, "main": "Clouds", "description": "few clouds", "icon": "02n"}], "clouds": {"all": 24}, "wind": {"speed": 2.86, "deg": 187.501}, "rain": {}, "sys": {"pod": "n"}, "dt_txt": "2019-01-12 00:00:00"}, {"dt": 1547262000, "main": {"temp": 22.35, "temp_min": 22.35, "temp_max": 22.35, "pressure": 991.68, "sea_level": 1024, "grnd_level": 991.68, "humidity": 86, "temp_kf": 0}, "weather": [{"id": 500, "main": "Rain", "description": "light rain", "icon": "10n"}], "clouds": {"all": 24}, "wind": {"speed": 2.71, "deg": 275.502}, "rain": {"3h": 0.050000000000001}, "sys": {"pod": "n"}, "dt_txt": "2019-01-12 03:00:00"}, {"dt": 1547272800, "main": {"temp": 21.35, "temp_min": 21.35, "temp_max": 21.35, "pressure": 992.22, "sea_level": 1024.78, "grnd_level": 992.22, "humidity": 90, "temp_kf": 0}, "weather": [{"id": 500, "main": "Rain", "description": "light rain", "icon": "10n"}], "clouds": {"all": 44}, "wind": {"speed": 3.25, "deg": 202}, "rain": {"3h": 0.08}, "sys": {"pod": "n"}, "dt_txt": "2019-01-12 06:00:00"}, {"dt": 1547283600, "main": {"temp": 25.93, "temp_min": 25.93, "temp_max": 25.93, "pressure": 993.53, "sea_level": 1025.92, "grnd_level": 993.53, "humidity": 71, "temp_kf": 0}, "weather": [{"id": 801, "main": "Clouds", "description": "few clouds", "icon": "02d"}], "clouds": {"all": 24}, "wind": {"speed": 2.67, "deg": 249.001}, "rain": {}, "sys": {"pod": "d"}, "dt_txt": "2019-01-12 09:00:00"}, {"dt": 1547294400, "main": {"temp": 32.81, "temp_min": 32.81, "temp_max": 32.81, "pressure": 992.19, "sea_level": 1024.26, "grnd_level": 992.19, "humidity": 52, "temp_kf": 0}, "weather": [{"id": 800, "main": "Clear", "description": "clear sky", "icon": "01d"}], "clouds": {"all": 0}, "wind": {"speed": 2.51, "deg": 325.502}, "rain": {}, "sys": {"pod": "d"}, "dt_txt": "2019-01-12 12:00:00"}, {"dt": 1547305200, "main": {"temp": 34.26, "temp_min": 34.26, "temp_max": 34.26, "pressure": 989.27, "sea_level": 1021.13, "grnd_level": 989.27, "humidity": 35, "temp_kf": 0}, "weather": [{"id": 800, "main": "Clear", "description": "clear sky", "icon": "02d"}], "clouds": {"all": 8}, "wind": {"speed": 4.82, "deg": 47.0001}, "rain": {}, "sys": {"pod": "d"}, "dt_txt": "2019-01-12 15:00:00"}, {"dt": 1547316000, "main": {"temp": 31.12, "temp_min": 31.12, "temp_max": 31.12, "pressure": 990.29, "sea_level": 1022.16, "grnd_level": 990.29, "humidity": 32, "temp_kf": 0}, "weather": [{"id": 800, "main": "Clear", "description": "clear sky", "icon": "02d"}], "clouds": {"all": 8}, "wind": {"speed": 2.86, "deg": 64.0007}, "rain": {}, "sys": {"pod": "d"}, "dt_txt": "2019-01-12 18:00:00"}, {"dt": 1547326800, "main": {"temp": 24.21, "temp_min": 24.21, "temp_max": 24.21, "pressure": 992.45, "sea_level": 1024.48, "grnd_level": 992.45, "humidity": 55, "temp_kf": 0}, "weather": [{"id": 800, "main": "Clear", "description": "clear sky", "icon": "01n"}], "clouds": {"all": 0}, "wind": {"speed": 1.34, "deg": 73.502}, "rain": {}, "sys": {"pod": "n"}, "dt_txt": "2019-01-12 21:00:00"}, {"dt": 1547337600, "main": {"temp": 21.79, "temp_min": 21.79, "temp_max": 21.79, "pressure": 992.2, "sea_level": 1024.58, "grnd_level": 992.2, "humidity": 67, "temp_kf": 0}, "weather": [{"id": 800, "main": "Clear", "description": "clear sky", "icon": "01n"}], "clouds": {"all": 0}, "wind": {"speed": 1.94, "deg": 200.502}, "rain": {}, "sys": {"pod": "n"}, "dt_txt": "2019-01-13 00:00:00"}, {"dt": 1547348400, "main": {"temp": 20.73, "temp_min": 20.73, "temp_max": 20.73, "pressure": 991.54, "sea_level": 1024.08, "grnd_level": 991.54, "humidity": 95, "temp_kf": 0}, "weather": [{"id": 800, "main": "Clear", "description": "clear sky", "icon": "01n"}], "clouds": {"all": 0}, "wind": {"speed": 3.53, "deg": 210.002}, "rain": {}, "sys": {"pod": "n"}, "dt_txt": "2019-01-13 03:00:00"}, {"dt": 1547359200, "main": {"temp": 20.04, "temp_min": 20.04, "temp_max": 20.04, "pressure": 992.93, "sea_level": 1025.61, "grnd_level": 992.93, "humidity": 95, "temp_kf": 0}, "weather": [{"id": 500, "main": "Rain", "description": "light rain", "icon": "10n"}], "clouds": {"all": 8}, "wind": {"speed": 2.71, "deg": 235.501}, "rain": {"3h": 0.0099999999999998}, "sys": {"pod": "n"}, "dt_txt": "2019-01-13 06:00:00"}, {"dt": 1547370000, "main": {"temp": 25.49, "temp_min": 25.49, "temp_max": 25.49, "pressure": 995.13, "sea_level": 1027.45, "grnd_level": 995.13, "humidity": 78, "temp_kf": 0}, "weather": [{"id": 801, "main": "Clouds", "description": "few clouds", "icon": "02d"}], "clouds": {"all": 24}, "wind": {"speed": 2.49, "deg": 244.5}, "rain": {}, "sys": {"pod": "d"}, "dt_txt": "2019-01-13 09:00:00"}, {"dt": 1547380800, "main": {"temp": 32.32, "temp_min": 32.32, "temp_max": 32.32, "pressure": 993.37, "sea_level": 1025.44, "grnd_level": 993.37, "humidity": 50, "temp_kf": 0}, "weather": [{"id": 800, "main": "Clear", "description": "clear sky", "icon": "01d"}], "clouds": {"all": 0}, "wind": {"speed": 2.27, "deg": 276.001}, "rain": {}, "sys": {"pod": "d"}, "dt_txt": "2019-01-13 12:00:00"}, {"dt": 1547391600, "main": {"temp": 34.06, "temp_min": 34.06, "temp_max": 34.06, "pressure": 990.63, "sea_level": 1022.47, "grnd_level": 990.63, "humidity": 39, "temp_kf": 0}, "weather": [{"id": 800, "main": "Clear", "description": "clear sky", "icon": "01d"}], "clouds": {"all": 0}, "wind": {"speed": 2.28, "deg": 21.0005}, "rain": {}, "sys": {"pod": "d"}, "dt_txt": "2019-01-13 15:00:00"}, {"dt": 1547402400, "main": {"temp": 31.15, "temp_min": 31.15, "temp_max": 31.15, "pressure": 991.16, "sea_level": 1023.23, "grnd_level": 991.16, "humidity": 31, "temp_kf": 0}, "weather": [{"id": 800, "main": "Clear", "description": "clear sky", "icon": "02d"}], "clouds": {"all": 8}, "wind": {"speed": 2.69, "deg": 28.5008}, "rain": {}, "sys": {"pod": "d"}, "dt_txt": "2019-01-13 18:00:00"}, {"dt": 1547413200, "main": {"temp": 25.14, "temp_min": 25.14, "temp_max": 25.14, "pressure": 993.77, "sea_level": 1025.95, "grnd_level": 993.77, "humidity": 34, "temp_kf": 0}, "weather": [{"id": 800, "main": "Clear", "description": "clear sky", "icon": "01n"}], "clouds": {"all": 0}, "wind": {"speed": 2.91, "deg": 21.0025}, "rain": {}, "sys": {"pod": "n"}, "dt_txt": "2019-01-13 21:00:00"}, {"dt": 1547424000, "main": {"temp": 21.53, "temp_min": 21.53, "temp_max": 21.53, "pressure": 993.7, "sea_level": 1026.05, "grnd_level": 993.7, "humidity": 55, "temp_kf": 0}, "weather": [{"id": 800, "main": "Clear", "description": "clear sky", "icon": "01n"}], "clouds": {"all": 0}, "wind": {"speed": 1.34, "deg": 22.5049}, "rain": {}, "sys": {"pod": "n"}, "dt_txt": "2019-01-14 00:00:00"}, {"dt": 1547434800, "main": {"temp": 20.05, "temp_min": 20.05, "temp_max": 20.05, "pressure": 992.62, "sea_level": 1025.03, "grnd_level": 992.62, "humidity": 85, "temp_kf": 0}, "weather": [{"id": 800, "main": "Clear", "description": "clear sky", "icon": "01n"}], "clouds": {"all": 0}, "wind": {"speed": 4.31, "deg": 213.5}, "rain": {}, "sys": {"pod": "n"}, "dt_txt": "2019-01-14 03:00:00"}, {"dt": 1547445600, "main": {"temp": 19.34, "temp_min": 19.34, "temp_max": 19.34, "pressure": 993.54, "sea_level": 1026.28, "grnd_level": 993.54, "humidity": 93, "temp_kf": 0}, "weather": [{"id": 800, "main": "Clear", "description": "clear sky", "icon": "01n"}], "clouds": {"all": 0}, "wind": {"speed": 2.46, "deg": 210.007}, "rain": {}, "sys": {"pod": "n"}, "dt_txt": "2019-01-14 06:00:00"}, {"dt": 1547456400, "main": {"temp": 27.47, "temp_min": 27.47, "temp_max": 27.47, "pressure": 995.12, "sea_level": 1027.52, "grnd_level": 995.12, "humidity": 64, "temp_kf": 0}, "weather": [{"id": 800, "main": "Clear", "description": "clear sky", "icon": "01d"}], "clouds": {"all": 0}, "wind": {"speed": 1.96, "deg": 216.003}, "rain": {}, "sys": {"pod": "d"}, "dt_txt": "2019-01-14 09:00:00"}, {"dt": 1547467200, "main": {"temp": 33.09, "temp_min": 33.09, "temp_max": 33.09, "pressure": 993.58, "sea_level": 1025.55, "grnd_level": 993.58, "humidity": 42, "temp_kf": 0}, "weather": [{"id": 800, "main": "Clear", "description": "clear sky", "icon": "01d"}], "clouds": {"all": 0}, "wind": {"speed": 2.22, "deg": 350.503}, "rain": {}, "sys": {"pod": "d"}, "dt_txt": "2019-01-14 12:00:00"}, {"dt": 1547478000, "main": {"temp": 34.36, "temp_min": 34.36, "temp_max": 34.36, "pressure": 990.78, "sea_level": 1022.59, "grnd_level": 990.78, "humidity": 33, "temp_kf": 0}, "weather": [{"id": 800, "main": "Clear", "description": "clear sky", "icon": "01d"}], "clouds": {"all": 0}, "wind": {"speed": 2.12, "deg": 25.5004}, "rain": {}, "sys": {"pod": "d"}, "dt_txt": "2019-01-14 15:00:00"}, {"dt": 1547488800, "main": {"temp": 30.75, "temp_min": 30.75, "temp_max": 30.75, "pressure": 991.23, "sea_level": 1023.19, "grnd_level": 991.23, "humidity": 30, "temp_kf": 0}, "weather": [{"id": 800, "main": "Clear", "description": "clear sky", "icon": "01d"}], "clouds": {"all": 0}, "wind": {"speed": 2.01, "deg": 18.0022}, "rain": {}, "sys": {"pod": "d"}, "dt_txt": "2019-01-14 18:00:00"}, {"dt": 1547499600, "main": {"temp": 24.54, "temp_min": 24.54, "temp_max": 24.54, "pressure": 993.4, "sea_level": 1025.54, "grnd_level": 993.4, "humidity": 36, "temp_kf": 0}, "weather": [{"id": 800, "main": "Clear", "description": "clear sky", "icon": "01n"}], "clouds": {"all": 0}, "wind": {"speed": 2.91, "deg": 5.5007}, "rain": {}, "sys": {"pod": "n"}, "dt_txt": "2019-01-14 21:00:00"}, {"dt": 1547510400, "main": {"temp": 21.42, "temp_min": 21.42, "temp_max": 21.42, "pressure": 993.22, "sea_level": 1025.47, "grnd_level": 993.22, "humidity": 51, "temp_kf": 0}, "weather": [{"id": 800, "main": "Clear", "description": "clear sky", "icon": "01n"}], "clouds": {"all": 0}, "wind": {"speed": 1.32, "deg": 356.502}, "rain": {}, "sys": {"pod": "n"}, "dt_txt": "2019-01-15 00:00:00"}, {"dt": 1547521200, "main": {"temp": 19.98, "temp_min": 19.98, "temp_max": 19.98, "pressure": 991.47, "sea_level": 1024.03, "grnd_level": 991.47, "humidity": 57, "temp_kf": 0}, "weather": [{"id": 801, "main": "Clouds", "description": "few clouds", "icon": "02n"}], "clouds": {"all": 12}, "wind": {"speed": 0.71, "deg": 306.501}, "rain": {}, "sys": {"pod": "n"}, "dt_txt": "2019-01-15 03:00:00"}, {"dt": 1547532000, "main": {"temp": 19.19, "temp_min": 19.19, "temp_max": 19.19, "pressure": 992.68, "sea_level": 1025.21, "grnd_level": 992.68, "humidity": 88, "temp_kf": 0}, "weather": [{"id": 803, "main": "Clouds", "description": "broken clouds", "icon": "04n"}], "clouds": {"all": 56}, "wind": {"speed": 1.72, "deg": 216.5}, "rain": {}, "sys": {"pod": "n"}, "dt_txt": "2019-01-15 06:00:00"}, {"dt": 1547542800, "main": {"temp": 27.16, "temp_min": 27.16, "temp_max": 27.16, "pressure": 994.66, "sea_level": 1026.97, "grnd_level": 994.66, "humidity": 65, "temp_kf": 0}, "weather": [{"id": 800, "main": "Clear", "description": "clear sky", "icon": "01d"}], "clouds": {"all": 0}, "wind": {"speed": 1.97, "deg": 239}, "rain": {}, "sys": {"pod": "d"}, "dt_txt": "2019-01-15 09:00:00"}, {"dt": 1547553600, "main": {"temp": 32.99, "temp_min": 32.99, "temp_max": 32.99, "pressure": 993.02, "sea_level": 1025.09, "grnd_level": 993.02, "humidity": 40, "temp_kf": 0}, "weather": [{"id": 800, "main": "Clear", "description": "clear sky", "icon": "01d"}], "clouds": {"all": 0}, "wind": {"speed": 1.88, "deg": 317.501}, "rain": {}, "sys": {"pod": "d"}, "dt_txt": "2019-01-15 12:00:00"}, {"dt": 1547564400, "main": {"temp": 34.34, "temp_min": 34.34, "temp_max": 34.34, "pressure": 990.4, "sea_level": 1022.19, "grnd_level": 990.4, "humidity": 32, "temp_kf": 0}, "weather": [{"id": 800, "main": "Clear", "description": "clear sky", "icon": "01d"}], "clouds": {"all": 0}, "wind": {"speed": 2.12, "deg": 7.50043}, "rain": {}, "sys": {"pod": "d"}, "dt_txt": "2019-01-15 15:00:00"}, {"dt": 1547575200, "main": {"temp": 31.18, "temp_min": 31.18, "temp_max": 31.18, "pressure": 991.01, "sea_level": 1022.79, "grnd_level": 991.01, "humidity": 29, "temp_kf": 0}, "weather": [{"id": 800, "main": "Clear", "description": "clear sky", "icon": "01d"}], "clouds": {"all": 0}, "wind": {"speed": 1.73, "deg": 6.50153}, "rain": {}, "sys": {"pod": "d"}, "dt_txt": "2019-01-15 18:00:00"}, {"dt": 1547586000, "main": {"temp": 25.41, "temp_min": 25.41, "temp_max": 25.41, "pressure": 993.16, "sea_level": 1025.21, "grnd_level": 993.16, "humidity": 38, "temp_kf": 0}, "weather": [{"id": 801, "main": "Clouds", "description": "few clouds", "icon": "02n"}], "clouds": {"all": 12}, "wind": {"speed": 2.82, "deg": 355.003}, "rain": {}, "sys": {"pod": "n"}, "dt_txt": "2019-01-15 21:00:00"}], "city": {"id": 2299625, "name": "Kintampo", "coord": {"lat": 8.0537, "lon": -1.729}, "country": "GH", "population": 22731}}