{"cod": "200", "message": 0.0037, "cnt": 39, "list": [{"dt": 1547175600, "main": {"temp": -5.85, "temp_min": -6.29, "temp_max": -5.85, "pressure": 1002.37, "sea_level": 1006.79, "grnd_level": 1002.37, "humidity": 84, "temp_kf": 0.44}, "weather": [{"id": 600, "main": "Snow", "description": "light snow", "icon": "13n"}], "clouds": {"all": 92}, "wind": {"speed": 11.26, "deg": 204.502}, "snow": {"3h": 0.479}, "sys": {"pod": "n"}, "dt_txt": "2019-01-11 03:00:00"}, {"dt": 1547186400, "main": {"temp": -5.21, "temp_min": -5.55, "temp_max": -5.21, "pressure": 997.72, "sea_level": 1002.14, "grnd_level": 997.72, "humidity": 83, "temp_kf": 0.33}, "weather": [{"id": 601, "main": "Snow", "description": "snow", "icon": "13n"}], "clouds": {"all": 92}, "wind": {"speed": 11.02, "deg": 213.004}, "snow": {"3h": 2.01}, "sys": {"pod": "n"}, "dt_txt": "2019-01-11 06:00:00"}, {"dt": 1547197200, "main": {"temp": -4.3, "temp_min": -4.52, "temp_max": -4.3, "pressure": 994.23, "sea_level": 998.66, "grnd_level": 994.23, "humidity": 84, "temp_kf": 0.22}, "weather": [{"id": 601, "main": "Snow", "description": "snow", "icon": "13d"}], "clouds": {"all": 92}, "wind": {"speed": 10.61, "deg": 208.004}, "snow": {"3h": 1.652}, "sys": {"pod": "d"}, "dt_txt": "2019-01-11 09:00:00"}, {"dt": 1547208000, "main": {"temp": -3.7, "temp_min": -3.82, "temp_max": -3.7, "pressure": 991.33, "sea_level": 995.78, "grnd_level": 991.33, "humidity": 86, "temp_kf": 0.11}, "weather": [{"id": 601, "main": "Snow", "description": "snow", "icon": "13d"}], "clouds": {"all": 88}, "wind": {"speed": 10.32, "deg": 203.501}, "snow": {"3h": 2.145}, "sys": {"pod": "d"}, "dt_txt": "2019-01-11 12:00:00"}, {"dt": 1547218800, "main": {"temp": -3.56, "temp_min": -3.56, "temp_max": -3.56, "pressure": 988.99, "sea_level": 993.46, "grnd_level": 988.99, "humidity": 81, "temp_kf": 0}, "weather": [{"id": 600, "main": "Snow", "description": "light snow", "icon": "13n"}], "clouds": {"all": 80}, "wind": {"speed": 10.15, "deg": 196.503}, "snow": {"3h": 1.17475}, "sys": {"pod": "n"}, "dt_txt": "2019-01-11 15:00:00"}, {"dt": 1547229600, "main": {"temp": -3.43, "temp_min": -3.43, "temp_max": -3.43, "pressure": 987.3, "sea_level": 991.66, "grnd_level": 987.3, "humidity": 80, "temp_kf": 0}, "weather": [{"id": 600, "main": "Snow", "description": "light snow", "icon": "13n"}], "clouds": {"all": 88}, "wind": {"speed": 9.71, "deg": 188}, "snow": {"3h": 0.335}, "sys": {"pod": "n"}, "dt_txt": "2019-01-11 18:00:00"}, {"dt": 1547240400, "main": {"temp": -2.88, "temp_min": -2.88, "temp_max": -2.88, "pressure": 985.44, "sea_level": 989.86, "grnd_level": 985.44, "humidity": 83, "temp_kf": 0}, "weather": [{"id": 600, "main": "Snow", "description": "light snow", "icon": "13n"}], "clouds": {"all": 88}, "wind": {"speed": 9.61, "deg": 184.5}, "snow": {"3h": 0.53375}, "sys": {"pod": "n"}, "dt_txt": "2019-01-11 21:00:00"}, {"dt": 1547251200, "main": {"temp": -2.51, "temp_min": -2.51, "temp_max": -2.51, "pressure": 983.82, "sea_level": 988.35, "grnd_level": 983.82, "humidity": 87, "temp_kf": 0}, "weather": [{"id": 600, "main": "Snow", "description": "light snow", "icon": "13n"}], "clouds": {"all": 88}, "wind": {"speed": 9.11, "deg": 185.501}, "snow": {"3h": 1.145}, "sys": {"pod": "n"}, "dt_txt": "2019-01-12 00:00:00"}, {"dt": 1547262000, "main": {"temp": -2.48, "temp_min": -2.48, "temp_max": -2.48, "pressure": 982.52, "sea_level": 987, "grnd_level": 982.52, "humidity": 86, "temp_kf": 0}, "weather": [{"id": 600, "main": "Snow", "description": "light snow", "icon": "13n"}], "clouds": {"all": 88}, "wind": {"speed": 8.26, "deg": 184.002}, "snow": {"3h": 1.0237}, "sys": {"pod": "n"}, "dt_txt": "2019-01-12 03:00:00"}, {"dt": 1547272800, "main": {"temp": -1.91, "temp_min": -1.91, "temp_max": -1.91, "pressure": 981.52, "sea_level": 986.03, "grnd_level": 981.52, "humidity": 86, "temp_kf": 0}, "weather": [{"id": 600, "main": "Snow", "description": "light snow", "icon": "13n"}], "clouds": {"all": 92}, "wind": {"speed": 7, "deg": 185}, "snow": {"3h": 1.145}, "sys": {"pod": "n"}, "dt_txt": "2019-01-12 06:00:00"}, {"dt": 1547283600, "main": {"temp": -1.13, "temp_min": -1.13, "temp_max": -1.13, "pressure": 982.02, "sea_level": 986.48, "grnd_level": 982.02, "humidity": 95, "temp_kf": 0}, "weather": [{"id": 601, "main": "Snow", "description": "snow", "icon": "13d"}], "clouds": {"all": 92}, "wind": {"speed": 4.57, "deg": 244.501}, "snow": {"3h": 2.2238}, "sys": {"pod": "d"}, "dt_txt": "2019-01-12 09:00:00"}, {"dt": 1547294400, "main": {"temp": -3.24, "temp_min": -3.24, "temp_max": -3.24, "pressure": 983.19, "sea_level": 987.63, "grnd_level": 983.19, "humidity": 85, "temp_kf": 0}, "weather": [{"id": 600, "main": "Snow", "description": "light snow", "icon": "13d"}], "clouds": {"all": 76}, "wind": {"speed": 3.96, "deg": 253.502}, "snow": {"3h": 0.255}, "sys": {"pod": "d"}, "dt_txt": "2019-01-12 12:00:00"}, {"dt": 1547305200, "main": {"temp": -3.57, "temp_min": -3.57, "temp_max": -3.57, "pressure": 983.6, "sea_level": 988.1, "grnd_level": 983.6, "humidity": 90, "temp_kf": 0}, "weather": [{"id": 600, "main": "Snow", "description": "light snow", "icon": "13n"}], "clouds": {"all": 80}, "wind": {"speed": 4.37, "deg": 224}, "snow": {"3h": 0.0862}, "sys": {"pod": "n"}, "dt_txt": "2019-01-12 15:00:00"}, {"dt": 1547316000, "main": {"temp": -2.51, "temp_min": -2.51, "temp_max": -2.51, "pressure": 983.64, "sea_level": 988.07, "grnd_level": 983.64, "humidity": 90, "temp_kf": 0}, "weather": [{"id": 600, "main": "Snow", "description": "light snow", "icon": "13n"}], "clouds": {"all": 88}, "wind": {"speed": 5.21, "deg": 237.501}, "snow": {"3h": 0.3063}, "sys": {"pod": "n"}, "dt_txt": "2019-01-12 18:00:00"}, {"dt": 1547326800, "main": {"temp": -2.4, "temp_min": -2.4, "temp_max": -2.4, "pressure": 983.78, "sea_level": 988.2, "grnd_level": 983.78, "humidity": 89, "temp_kf": 0}, "weather": [{"id": 600, "main": "Snow", "description": "light snow", "icon": "13n"}], "clouds": {"all": 88}, "wind": {"speed": 5.74, "deg": 239.002}, "snow": {"3h": 0.505}, "sys": {"pod": "n"}, "dt_txt": "2019-01-12 21:00:00"}, {"dt": 1547337600, "main": {"temp": -2.74, "temp_min": -2.74, "temp_max": -2.74, "pressure": 984.1, "sea_level": 988.43, "grnd_level": 984.1, "humidity": 91, "temp_kf": 0}, "weather": [{"id": 600, "main": "Snow", "description": "light snow", "icon": "13n"}], "clouds": {"all": 92}, "wind": {"speed": 6.07, "deg": 233.502}, "snow": {"3h": 0.435}, "sys": {"pod": "n"}, "dt_txt": "2019-01-13 00:00:00"}, {"dt": 1547348400, "main": {"temp": -4.08, "temp_min": -4.08, "temp_max": -4.08, "pressure": 983.92, "sea_level": 988.33, "grnd_level": 983.92, "humidity": 84, "temp_kf": 0}, "weather": [{"id": 600, "main": "Snow", "description": "light snow", "icon": "13n"}], "clouds": {"all": 88}, "wind": {"speed": 6.01, "deg": 223.502}, "snow": {"3h": 0.09}, "sys": {"pod": "n"}, "dt_txt": "2019-01-13 03:00:00"}, {"dt": 1547359200, "main": {"temp": -4.02, "temp_min": -4.02, "temp_max": -4.02, "pressure": 983.93, "sea_level": 988.4, "grnd_level": 983.93, "humidity": 90, "temp_kf": 0}, "weather": [{"id": 600, "main": "Snow", "description": "light snow", "icon": "13n"}], "clouds": {"all": 88}, "wind": {"speed": 6.06, "deg": 222.501}, "snow": {"3h": 0.695}, "sys": {"pod": "n"}, "dt_txt": "2019-01-13 06:00:00"}, {"dt": 1547370000, "main": {"temp": -3.11, "temp_min": -3.11, "temp_max": -3.11, "pressure": 984.43, "sea_level": 988.9, "grnd_level": 984.43, "humidity": 91, "temp_kf": 0}, "weather": [{"id": 600, "main": "Snow", "description": "light snow", "icon": "13d"}], "clouds": {"all": 88}, "wind": {"speed": 5.27, "deg": 232}, "snow": {"3h": 0.265}, "sys": {"pod": "d"}, "dt_txt": "2019-01-13 09:00:00"}, {"dt": 1547380800, "main": {"temp": -3.03, "temp_min": -3.03, "temp_max": -3.03, "pressure": 985.02, "sea_level": 989.49, "grnd_level": 985.02, "humidity": 90, "temp_kf": 0}, "weather": [{"id": 600, "main": "Snow", "description": "light snow", "icon": "13d"}], "clouds": {"all": 88}, "wind": {"speed": 5.65, "deg": 233.501}, "snow": {"3h": 0.435}, "sys": {"pod": "d"}, "dt_txt": "2019-01-13 12:00:00"}, {"dt": 1547391600, "main": {"temp": -3.27, "temp_min": -3.27, "temp_max": -3.27, "pressure": 986.01, "sea_level": 990.33, "grnd_level": 986.01, "humidity": 92, "temp_kf": 0}, "weather": [{"id": 600, "main": "Snow", "description": "light snow", "icon": "13n"}], "clouds": {"all": 88}, "wind": {"speed": 5.41, "deg": 229.5}, "snow": {"3h": 0.4275}, "sys": {"pod": "n"}, "dt_txt": "2019-01-13 15:00:00"}, {"dt": 1547402400, "main": {"temp": -3.63, "temp_min": -3.63, "temp_max": -3.63, "pressure": 986.62, "sea_level": 990.97, "grnd_level": 986.62, "humidity": 91, "temp_kf": 0}, "weather": [{"id": 600, "main": "Snow", "description": "light snow", "icon": "13n"}], "clouds": {"all": 88}, "wind": {"speed": 5.87, "deg": 225.501}, "snow": {"3h": 0.665}, "sys": {"pod": "n"}, "dt_txt": "2019-01-13 18:00:00"}, {"dt": 1547413200, "main": {"temp": -4.37, "temp_min": -4.37, "temp_max": -4.37, "pressure": 987.37, "sea_level": 991.74, "grnd_level": 987.37, "humidity": 89, "temp_kf": 0}, "weather": [{"id": 600, "main": "Snow", "description": "light snow", "icon": "13n"}], "clouds": {"all": 88}, "wind": {"speed": 5.38, "deg": 218.002}, "snow": {"3h": 0.455}, "sys": {"pod": "n"}, "dt_txt": "2019-01-13 21:00:00"}, {"dt": 1547424000, "main": {"temp": -5.48, "temp_min": -5.48, "temp_max": -5.48, "pressure": 988.27, "sea_level": 992.61, "grnd_level": 988.27, "humidity": 89, "temp_kf": 0}, "weather": [{"id": 600, "main": "Snow", "description": "light snow", "icon": "13n"}], "clouds": {"all": 88}, "wind": {"speed": 5.04, "deg": 210.505}, "snow": {"3h": 0.22}, "sys": {"pod": "n"}, "dt_txt": "2019-01-14 00:00:00"}, {"dt": 1547434800, "main": {"temp": -5.9, "temp_min": -5.9, "temp_max": -5.9, "pressure": 988.72, "sea_level": 993.18, "grnd_level": 988.72, "humidity": 88, "temp_kf": 0}, "weather": [{"id": 600, "main": "Snow", "description": "light snow", "icon": "13n"}], "clouds": {"all": 80}, "wind": {"speed": 4.66, "deg": 203}, "snow": {"3h": 0.255}, "sys": {"pod": "n"}, "dt_txt": "2019-01-14 03:00:00"}, {"dt": 1547445600, "main": {"temp": -5.77, "temp_min": -5.77, "temp_max": -5.77, "pressure": 989.08, "sea_level": 993.65, "grnd_level": 989.08, "humidity": 88, "temp_kf": 0}, "weather": [{"id": 600, "main": "Snow", "description": "light snow", "icon": "13n"}], "clouds": {"all": 88}, "wind": {"speed": 4.71, "deg": 187.507}, "snow": {"3h": 0.28}, "sys": {"pod": "n"}, "dt_txt": "2019-01-14 06:00:00"}, {"dt": 1547456400, "main": {"temp": -5.54, "temp_min": -5.54, "temp_max": -5.54, "pressure": 990.34, "sea_level": 994.85, "grnd_level": 990.34, "humidity": 90, "temp_kf": 0}, "weather": [{"id": 600, "main": "Snow", "description": "light snow", "icon": "13d"}], "clouds": {"all": 80}, "wind": {"speed": 4.86, "deg": 186.503}, "snow": {"3h": 0.3825}, "sys": {"pod": "d"}, "dt_txt": "2019-01-14 09:00:00"}, {"dt": 1547467200, "main": {"temp": -5.22, "temp_min": -5.22, "temp_max": -5.22, "pressure": 992.04, "sea_level": 996.53, "grnd_level": 992.04, "humidity": 88, "temp_kf": 0}, "weather": [{"id": 600, "main": "Snow", "description": "light snow", "icon": "13d"}], "clouds": {"all": 88}, "wind": {"speed": 4.22, "deg": 213.003}, "snow": {"3h": 0.43}, "sys": {"pod": "d"}, "dt_txt": "2019-01-14 12:00:00"}, {"dt": 1547478000, "main": {"temp": -5.85, "temp_min": -5.85, "temp_max": -5.85, "pressure": 993.86, "sea_level": 998.32, "grnd_level": 993.86, "humidity": 85, "temp_kf": 0}, "weather": [{"id": 600, "main": "Snow", "description": "light snow", "icon": "13n"}], "clouds": {"all": 80}, "wind": {"speed": 2.82, "deg": 209}, "snow": {"3h": 0.072500000000002}, "sys": {"pod": "n"}, "dt_txt": "2019-01-14 15:00:00"}, {"dt": 1547488800, "main": {"temp": -6.76, "temp_min": -6.76, "temp_max": -6.76, "pressure": 994.96, "sea_level": 999.44, "grnd_level": 994.96, "humidity": 86, "temp_kf": 0}, "weather": [{"id": 600, "main": "Snow", "description": "light snow", "icon": "13n"}], "clouds": {"all": 56}, "wind": {"speed": 2.96, "deg": 166.502}, "snow": {"3h": 0.055}, "sys": {"pod": "n"}, "dt_txt": "2019-01-14 18:00:00"}, {"dt": 1547499600, "main": {"temp": -7.79, "temp_min": -7.79, "temp_max": -7.79, "pressure": 996.08, "sea_level": 1000.54, "grnd_level": 996.08, "humidity": 84, "temp_kf": 0}, "weather": [{"id": 800, "main": "Clear", "description": "clear sky", "icon": "01n"}], "clouds": {"all": 68}, "wind": {"speed": 3.01, "deg": 166.001}, "snow": {"3h": 0.012499999999999}, "sys": {"pod": "n"}, "dt_txt": "2019-01-14 21:00:00"}, {"dt": 1547510400, "main": {"temp": -9.28, "temp_min": -9.28, "temp_max": -9.28, "pressure": 996.62, "sea_level": 1001.19, "grnd_level": 996.62, "humidity": 90, "temp_kf": 0}, "weather": [{"id": 800, "main": "Clear", "description": "clear sky", "icon": "01n"}], "clouds": {"all": 48}, "wind": {"speed": 2.07, "deg": 141.002}, "snow": {"3h": 0.0050000000000026}, "sys": {"pod": "n"}, "dt_txt": "2019-01-15 00:00:00"}, {"dt": 1547521200, "main": {"temp": -10.62, "temp_min": -10.62, "temp_max": -10.62, "pressure": 997.07, "sea_level": 1001.66, "grnd_level": 997.07, "humidity": 82, "temp_kf": 0}, "weather": [{"id": 800, "main": "Clear", "description": "clear sky", "icon": "01n"}], "clouds": {"all": 48}, "wind": {"speed": 1.31, "deg": 115.501}, "snow": {"3h": 0.0024999999999977}, "sys": {"pod": "n"}, "dt_txt": "2019-01-15 03:00:00"}, {"dt": 1547532000, "main": {"temp": -10.77, "temp_min": -10.77, "temp_max": -10.77, "pressure": 997.38, "sea_level": 1001.94, "grnd_level": 997.38, "humidity": 77, "temp_kf": 0}, "weather": [{"id": 803, "main": "Clouds", "description": "broken clouds", "icon": "04n"}], "clouds": {"all": 56}, "wind": {"speed": 1.12, "deg": 40.0004}, "snow": {}, "sys": {"pod": "n"}, "dt_txt": "2019-01-15 06:00:00"}, {"dt": 1547542800, "main": {"temp": -9.84, "temp_min": -9.84, "temp_max": -9.84, "pressure": 997.75, "sea_level": 1002.37, "grnd_level": 997.75, "humidity": 88, "temp_kf": 0}, "weather": [{"id": 800, "main": "Clear", "description": "clear sky", "icon": "01d"}], "clouds": {"all": 48}, "wind": {"speed": 1.82, "deg": 20.5005}, "snow": {"3h": 0.0050000000000026}, "sys": {"pod": "d"}, "dt_txt": "2019-01-15 09:00:00"}, {"dt": 1547553600, "main": {"temp": -9.36, "temp_min": -9.36, "temp_max": -9.36, "pressure": 997.97, "sea_level": 1002.52, "grnd_level": 997.97, "humidity": 85, "temp_kf": 0}, "weather": [{"id": 800, "main": "Clear", "description": "clear sky", "icon": "01d"}], "clouds": {"all": 68}, "wind": {"speed": 2.53, "deg": 10.0005}, "snow": {"3h": 0.004999999999999}, "sys": {"pod": "d"}, "dt_txt": "2019-01-15 12:00:00"}, {"dt": 1547564400, "main": {"temp": -9.39, "temp_min": -9.39, "temp_max": -9.39, "pressure": 998.02, "sea_level": 1002.65, "grnd_level": 998.02, "humidity": 90, "temp_kf": 0}, "weather": [{"id": 800, "main": "Clear", "description": "clear sky", "icon": "01n"}], "clouds": {"all": 80}, "wind": {"speed": 3.12, "deg": 356}, "snow": {"3h": 0.02}, "sys": {"pod": "n"}, "dt_txt": "2019-01-15 15:00:00"}, {"dt": 1547575200, "main": {"temp": -8.48, "temp_min": -8.48, "temp_max": -8.48, "pressure": 997.33, "sea_level": 1001.88, "grnd_level": 997.33, "humidity": 89, "temp_kf": 0}, "weather": [{"id": 600, "main": "Snow", "description": "light snow", "icon": "13n"}], "clouds": {"all": 88}, "wind": {"speed": 3.75, "deg": 351.002}, "snow": {"3h": 0.085000000000001}, "sys": {"pod": "n"}, "dt_txt": "2019-01-15 18:00:00"}, {"dt": 1547586000, "main": {"temp": -7.87, "temp_min": -7.87, "temp_max": -7.87, "pressure": 996.4, "sea_level": 1000.89, "grnd_level": 996.4, "humidity": 94, "temp_kf": 0}, "weather": [{"id": 600, "main": "Snow", "description": "light snow", "icon": "13n"}], "clouds": {"all": 88}, "wind": {"speed": 4.52, "deg": 339.503}, "snow": {"3h": 0.4275}, "sys": {"pod": "n"}, "dt_txt": "2019-01-15 21:00:00"}], "city": {"id": 515246, "name": "Onega", "coord": {"lat": 63.9116, "lon": 38.0948}, "country": "RU", "population": 22693}}