{"cod": "200", "message": 0.0035, "cnt": 39, "list": [{"dt": 1547175600, "main": {"temp": -18.7, "temp_min": -19.34, "temp_max": -18.7, "pressure": 795.43, "sea_level": 1045.62, "grnd_level": 795.43, "humidity": 86, "temp_kf": 0.64}, "weather": [{"id": 600, "main": "Snow", "description": "light snow", "icon": "13d"}], "clouds": {"all": 68}, "wind": {"speed": 1.06, "deg": 249.502}, "snow": {"3h": 0.158}, "sys": {"pod": "d"}, "dt_txt": "2019-01-11 03:00:00"}, {"dt": 1547186400, "main": {"temp": -13.39, "temp_min": -13.87, "temp_max": -13.39, "pressure": 796.04, "sea_level": 1043.96, "grnd_level": 796.04, "humidity": 79, "temp_kf": 0.48}, "weather": [{"id": 600, "main": "Snow", "description": "light snow", "icon": "13d"}], "clouds": {"all": 0}, "wind": {"speed": 0.52, "deg": 201.504}, "snow": {"3h": 0.041}, "sys": {"pod": "d"}, "dt_txt": "2019-01-11 06:00:00"}, {"dt": 1547197200, "main": {"temp": -12.92, "temp_min": -13.25, "temp_max": -12.92, "pressure": 795.88, "sea_level": 1042.8, "grnd_level": 795.88, "humidity": 75, "temp_kf": 0.32}, "weather": [{"id": 800, "main": "Clear", "description": "clear sky", "icon": "01d"}], "clouds": {"all": 0}, "wind": {"speed": 0.16, "deg": 181.504}, "snow": {}, "sys": {"pod": "d"}, "dt_txt": "2019-01-11 09:00:00"}, {"dt": 1547208000, "main": {"temp": -22.83, "temp_min": -22.99, "temp_max": -22.83, "pressure": 796.63, "sea_level": 1046.23, "grnd_level": 796.63, "humidity": 66, "temp_kf": 0.16}, "weather": [{"id": 800, "main": "Clear", "description": "clear sky", "icon": "01n"}], "clouds": {"all": 0}, "wind": {"speed": 1.47, "deg": 163.001}, "snow": {}, "sys": {"pod": "n"}, "dt_txt": "2019-01-11 12:00:00"}, {"dt": 1547218800, "main": {"temp": -24.66, "temp_min": -24.66, "temp_max": -24.66, "pressure": 796.72, "sea_level": 1047.33, "grnd_level": 796.72, "humidity": 61, "temp_kf": 0}, "weather": [{"id": 800, "main": "Clear", "description": "clear sky", "icon": "01n"}], "clouds": {"all": 8}, "wind": {"speed": 1.6, "deg": 172.003}, "snow": {"3h": 0.00050000000000006}, "sys": {"pod": "n"}, "dt_txt": "2019-01-11 15:00:00"}, {"dt": 1547229600, "main": {"temp": -24.03, "temp_min": -24.03, "temp_max": -24.03, "pressure": 796.57, "sea_level": 1047.47, "grnd_level": 796.57, "humidity": 73, "temp_kf": 0}, "weather": [{"id": 800, "main": "Clear", "description": "clear sky", "icon": "01n"}], "clouds": {"all": 32}, "wind": {"speed": 1.56, "deg": 177.5}, "snow": {"3h": 0.015}, "sys": {"pod": "n"}, "dt_txt": "2019-01-11 18:00:00"}, {"dt": 1547240400, "main": {"temp": -23.33, "temp_min": -23.33, "temp_max": -23.33, "pressure": 796.57, "sea_level": 1047.62, "grnd_level": 796.57, "humidity": 82, "temp_kf": 0}, "weather": [{"id": 800, "main": "Clear", "description": "clear sky", "icon": "01n"}], "clouds": {"all": 56}, "wind": {"speed": 1.51, "deg": 182.5}, "snow": {"3h": 0.0087499999999999}, "sys": {"pod": "n"}, "dt_txt": "2019-01-11 21:00:00"}, {"dt": 1547251200, "main": {"temp": -23.61, "temp_min": -23.61, "temp_max": -23.61, "pressure": 796.9, "sea_level": 1047.88, "grnd_level": 796.9, "humidity": 84, "temp_kf": 0}, "weather": [{"id": 600, "main": "Snow", "description": "light snow", "icon": "13n"}], "clouds": {"all": 44}, "wind": {"speed": 1.11, "deg": 179.501}, "snow": {"3h": 0.03125}, "sys": {"pod": "n"}, "dt_txt": "2019-01-12 00:00:00"}, {"dt": 1547262000, "main": {"temp": -23.05, "temp_min": -23.05, "temp_max": -23.05, "pressure": 797.63, "sea_level": 1048.56, "grnd_level": 797.63, "humidity": 80, "temp_kf": 0}, "weather": [{"id": 600, "main": "Snow", "description": "light snow", "icon": "13d"}], "clouds": {"all": 56}, "wind": {"speed": 1.01, "deg": 171.502}, "snow": {"3h": 0.04375}, "sys": {"pod": "d"}, "dt_txt": "2019-01-12 03:00:00"}, {"dt": 1547272800, "main": {"temp": -14.33, "temp_min": -14.33, "temp_max": -14.33, "pressure": 798.33, "sea_level": 1046.67, "grnd_level": 798.33, "humidity": 70, "temp_kf": 0}, "weather": [{"id": 600, "main": "Snow", "description": "light snow", "icon": "13d"}], "clouds": {"all": 68}, "wind": {"speed": 1.3, "deg": 175.5}, "snow": {"3h": 0.1225}, "sys": {"pod": "d"}, "dt_txt": "2019-01-12 06:00:00"}, {"dt": 1547283600, "main": {"temp": -11.5, "temp_min": -11.5, "temp_max": -11.5, "pressure": 799.39, "sea_level": 1047.11, "grnd_level": 799.39, "humidity": 76, "temp_kf": 0}, "weather": [{"id": 600, "main": "Snow", "description": "light snow", "icon": "13d"}], "clouds": {"all": 64}, "wind": {"speed": 1.52, "deg": 281.501}, "snow": {"3h": 0.17125}, "sys": {"pod": "d"}, "dt_txt": "2019-01-12 09:00:00"}, {"dt": 1547294400, "main": {"temp": -13.84, "temp_min": -13.84, "temp_max": -13.84, "pressure": 801.21, "sea_level": 1051.14, "grnd_level": 801.21, "humidity": 73, "temp_kf": 0}, "weather": [{"id": 600, "main": "Snow", "description": "light snow", "icon": "13n"}], "clouds": {"all": 64}, "wind": {"speed": 2.01, "deg": 286.502}, "snow": {"3h": 0.12}, "sys": {"pod": "n"}, "dt_txt": "2019-01-12 12:00:00"}, {"dt": 1547305200, "main": {"temp": -15.09, "temp_min": -15.09, "temp_max": -15.09, "pressure": 802.59, "sea_level": 1053.84, "grnd_level": 802.59, "humidity": 81, "temp_kf": 0}, "weather": [{"id": 600, "main": "Snow", "description": "light snow", "icon": "13n"}], "clouds": {"all": 64}, "wind": {"speed": 1.67, "deg": 285.5}, "snow": {"3h": 0.11125}, "sys": {"pod": "n"}, "dt_txt": "2019-01-12 15:00:00"}, {"dt": 1547316000, "main": {"temp": -17.14, "temp_min": -17.14, "temp_max": -17.14, "pressure": 803.69, "sea_level": 1055.72, "grnd_level": 803.69, "humidity": 80, "temp_kf": 0}, "weather": [{"id": 600, "main": "Snow", "description": "light snow", "icon": "13n"}], "clouds": {"all": 56}, "wind": {"speed": 1.21, "deg": 269.001}, "snow": {"3h": 0.07125}, "sys": {"pod": "n"}, "dt_txt": "2019-01-12 18:00:00"}, {"dt": 1547326800, "main": {"temp": -18.77, "temp_min": -18.77, "temp_max": -18.77, "pressure": 804.31, "sea_level": 1056.86, "grnd_level": 804.31, "humidity": 83, "temp_kf": 0}, "weather": [{"id": 600, "main": "Snow", "description": "light snow", "icon": "13n"}], "clouds": {"all": 56}, "wind": {"speed": 0.99, "deg": 214.002}, "snow": {"3h": 0.07}, "sys": {"pod": "n"}, "dt_txt": "2019-01-12 21:00:00"}, {"dt": 1547337600, "main": {"temp": -20.02, "temp_min": -20.02, "temp_max": -20.02, "pressure": 804.87, "sea_level": 1058.02, "grnd_level": 804.87, "humidity": 72, "temp_kf": 0}, "weather": [{"id": 600, "main": "Snow", "description": "light snow", "icon": "13n"}], "clouds": {"all": 44}, "wind": {"speed": 0.94, "deg": 187.002}, "snow": {"3h": 0.03}, "sys": {"pod": "n"}, "dt_txt": "2019-01-13 00:00:00"}, {"dt": 1547348400, "main": {"temp": -20.73, "temp_min": -20.73, "temp_max": -20.73, "pressure": 805.99, "sea_level": 1059.26, "grnd_level": 805.99, "humidity": 66, "temp_kf": 0}, "weather": [{"id": 800, "main": "Clear", "description": "clear sky", "icon": "01d"}], "clouds": {"all": 48}, "wind": {"speed": 1.03, "deg": 181.502}, "snow": {"3h": 0.0050000000000001}, "sys": {"pod": "d"}, "dt_txt": "2019-01-13 03:00:00"}, {"dt": 1547359200, "main": {"temp": -14.27, "temp_min": -14.27, "temp_max": -14.27, "pressure": 806.57, "sea_level": 1057.14, "grnd_level": 806.57, "humidity": 76, "temp_kf": 0}, "weather": [{"id": 800, "main": "Clear", "description": "clear sky", "icon": "01d"}], "clouds": {"all": 56}, "wind": {"speed": 1.36, "deg": 167.001}, "snow": {"3h": 0.0074999999999998}, "sys": {"pod": "d"}, "dt_txt": "2019-01-13 06:00:00"}, {"dt": 1547370000, "main": {"temp": -13.06, "temp_min": -13.06, "temp_max": -13.06, "pressure": 806.91, "sea_level": 1056.42, "grnd_level": 806.91, "humidity": 75, "temp_kf": 0}, "weather": [{"id": 801, "main": "Clouds", "description": "few clouds", "icon": "02d"}], "clouds": {"all": 12}, "wind": {"speed": 0.72, "deg": 152.5}, "snow": {}, "sys": {"pod": "d"}, "dt_txt": "2019-01-13 09:00:00"}, {"dt": 1547380800, "main": {"temp": -21.78, "temp_min": -21.78, "temp_max": -21.78, "pressure": 808.07, "sea_level": 1060.25, "grnd_level": 808.07, "humidity": 60, "temp_kf": 0}, "weather": [{"id": 800, "main": "Clear", "description": "clear sky", "icon": "01n"}], "clouds": {"all": 0}, "wind": {"speed": 1.07, "deg": 177.501}, "snow": {}, "sys": {"pod": "n"}, "dt_txt": "2019-01-13 12:00:00"}, {"dt": 1547391600, "main": {"temp": -25.12, "temp_min": -25.12, "temp_max": -25.12, "pressure": 808.65, "sea_level": 1062.23, "grnd_level": 808.65, "humidity": 65, "temp_kf": 0}, "weather": [{"id": 800, "main": "Clear", "description": "clear sky", "icon": "01n"}], "clouds": {"all": 0}, "wind": {"speed": 1.48, "deg": 177}, "snow": {}, "sys": {"pod": "n"}, "dt_txt": "2019-01-13 15:00:00"}, {"dt": 1547402400, "main": {"temp": -25.51, "temp_min": -25.51, "temp_max": -25.51, "pressure": 808.94, "sea_level": 1063.44, "grnd_level": 808.94, "humidity": 34, "temp_kf": 0}, "weather": [{"id": 800, "main": "Clear", "description": "clear sky", "icon": "01n"}], "clouds": {"all": 0}, "wind": {"speed": 1.69, "deg": 166.501}, "snow": {}, "sys": {"pod": "n"}, "dt_txt": "2019-01-13 18:00:00"}, {"dt": 1547413200, "main": {"temp": -25.69, "temp_min": -25.69, "temp_max": -25.69, "pressure": 809.12, "sea_level": 1064.21, "grnd_level": 809.12, "humidity": 34, "temp_kf": 0}, "weather": [{"id": 800, "main": "Clear", "description": "clear sky", "icon": "01n"}], "clouds": {"all": 0}, "wind": {"speed": 1.81, "deg": 162.502}, "snow": {}, "sys": {"pod": "n"}, "dt_txt": "2019-01-13 21:00:00"}, {"dt": 1547424000, "main": {"temp": -27.63, "temp_min": -27.63, "temp_max": -27.63, "pressure": 809.37, "sea_level": 1064.79, "grnd_level": 809.37, "humidity": 41, "temp_kf": 0}, "weather": [{"id": 800, "main": "Clear", "description": "clear sky", "icon": "01n"}], "clouds": {"all": 0}, "wind": {"speed": 1.14, "deg": 152.005}, "snow": {}, "sys": {"pod": "n"}, "dt_txt": "2019-01-14 00:00:00"}, {"dt": 1547434800, "main": {"temp": -28.5, "temp_min": -28.5, "temp_max": -28.5, "pressure": 809.74, "sea_level": 1065.24, "grnd_level": 809.74, "humidity": 44, "temp_kf": 0}, "weather": [{"id": 800, "main": "Clear", "description": "clear sky", "icon": "01d"}], "clouds": {"all": 0}, "wind": {"speed": 0.96, "deg": 146.5}, "snow": {}, "sys": {"pod": "d"}, "dt_txt": "2019-01-14 03:00:00"}, {"dt": 1547445600, "main": {"temp": -15.97, "temp_min": -15.97, "temp_max": -15.97, "pressure": 809.37, "sea_level": 1061.14, "grnd_level": 809.37, "humidity": 66, "temp_kf": 0}, "weather": [{"id": 800, "main": "Clear", "description": "clear sky", "icon": "01d"}], "clouds": {"all": 0}, "wind": {"speed": 1.28, "deg": 149.007}, "snow": {}, "sys": {"pod": "d"}, "dt_txt": "2019-01-14 06:00:00"}, {"dt": 1547456400, "main": {"temp": -14.19, "temp_min": -14.19, "temp_max": -14.19, "pressure": 809.01, "sea_level": 1058.81, "grnd_level": 809.01, "humidity": 76, "temp_kf": 0}, "weather": [{"id": 800, "main": "Clear", "description": "clear sky", "icon": "01d"}], "clouds": {"all": 0}, "wind": {"speed": 1.04, "deg": 140.503}, "snow": {}, "sys": {"pod": "d"}, "dt_txt": "2019-01-14 09:00:00"}, {"dt": 1547467200, "main": {"temp": -24.32, "temp_min": -24.32, "temp_max": -24.32, "pressure": 809.08, "sea_level": 1061.42, "grnd_level": 809.08, "humidity": 60, "temp_kf": 0}, "weather": [{"id": 800, "main": "Clear", "description": "clear sky", "icon": "01n"}], "clouds": {"all": 0}, "wind": {"speed": 0.97, "deg": 142.003}, "snow": {}, "sys": {"pod": "n"}, "dt_txt": "2019-01-14 12:00:00"}, {"dt": 1547478000, "main": {"temp": -28.65, "temp_min": -28.65, "temp_max": -28.65, "pressure": 808.96, "sea_level": 1062.11, "grnd_level": 808.96, "humidity": 22, "temp_kf": 0}, "weather": [{"id": 800, "main": "Clear", "description": "clear sky", "icon": "01n"}], "clouds": {"all": 0}, "wind": {"speed": 0.97, "deg": 141.5}, "snow": {}, "sys": {"pod": "n"}, "dt_txt": "2019-01-14 15:00:00"}, {"dt": 1547488800, "main": {"temp": -30.33, "temp_min": -30.33, "temp_max": -30.33, "pressure": 808.28, "sea_level": 1061.73, "grnd_level": 808.28, "humidity": 26, "temp_kf": 0}, "weather": [{"id": 800, "main": "Clear", "description": "clear sky", "icon": "01n"}], "clouds": {"all": 0}, "wind": {"speed": 0.96, "deg": 140.502}, "snow": {}, "sys": {"pod": "n"}, "dt_txt": "2019-01-14 18:00:00"}, {"dt": 1547499600, "main": {"temp": -31.29, "temp_min": -31.29, "temp_max": -31.29, "pressure": 807.37, "sea_level": 1060.84, "grnd_level": 807.37, "humidity": 29, "temp_kf": 0}, "weather": [{"id": 800, "main": "Clear", "description": "clear sky", "icon": "01n"}], "clouds": {"all": 0}, "wind": {"speed": 0.96, "deg": 141.001}, "snow": {}, "sys": {"pod": "n"}, "dt_txt": "2019-01-14 21:00:00"}, {"dt": 1547510400, "main": {"temp": -32.08, "temp_min": -32.08, "temp_max": -32.08, "pressure": 806.21, "sea_level": 1059.92, "grnd_level": 806.21, "humidity": 31, "temp_kf": 0}, "weather": [{"id": 800, "main": "Clear", "description": "clear sky", "icon": "01n"}], "clouds": {"all": 0}, "wind": {"speed": 0.97, "deg": 143.002}, "snow": {}, "sys": {"pod": "n"}, "dt_txt": "2019-01-15 00:00:00"}, {"dt": 1547521200, "main": {"temp": -31.62, "temp_min": -31.62, "temp_max": -31.62, "pressure": 805.6, "sea_level": 1058.85, "grnd_level": 805.6, "humidity": 30, "temp_kf": 0}, "weather": [{"id": 800, "main": "Clear", "description": "clear sky", "icon": "01d"}], "clouds": {"all": 0}, "wind": {"speed": 0.96, "deg": 142.501}, "snow": {}, "sys": {"pod": "d"}, "dt_txt": "2019-01-15 03:00:00"}, {"dt": 1547532000, "main": {"temp": -17.77, "temp_min": -17.77, "temp_max": -17.77, "pressure": 804.06, "sea_level": 1053.66, "grnd_level": 804.06, "humidity": 59, "temp_kf": 0}, "weather": [{"id": 800, "main": "Clear", "description": "clear sky", "icon": "01d"}], "clouds": {"all": 0}, "wind": {"speed": 1.22, "deg": 150.5}, "snow": {}, "sys": {"pod": "d"}, "dt_txt": "2019-01-15 06:00:00"}, {"dt": 1547542800, "main": {"temp": -15.79, "temp_min": -15.79, "temp_max": -15.79, "pressure": 802.96, "sea_level": 1051.04, "grnd_level": 802.96, "humidity": 79, "temp_kf": 0}, "weather": [{"id": 800, "main": "Clear", "description": "clear sky", "icon": "01d"}], "clouds": {"all": 0}, "wind": {"speed": 1.02, "deg": 148}, "snow": {}, "sys": {"pod": "d"}, "dt_txt": "2019-01-15 09:00:00"}, {"dt": 1547553600, "main": {"temp": -26.51, "temp_min": -26.51, "temp_max": -26.51, "pressure": 802.53, "sea_level": 1053.34, "grnd_level": 802.53, "humidity": 37, "temp_kf": 0}, "weather": [{"id": 800, "main": "Clear", "description": "clear sky", "icon": "01n"}], "clouds": {"all": 0}, "wind": {"speed": 0.98, "deg": 144.001}, "snow": {}, "sys": {"pod": "n"}, "dt_txt": "2019-01-15 12:00:00"}, {"dt": 1547564400, "main": {"temp": -30.82, "temp_min": -30.82, "temp_max": -30.82, "pressure": 802.1, "sea_level": 1054, "grnd_level": 802.1, "humidity": 55, "temp_kf": 0}, "weather": [{"id": 800, "main": "Clear", "description": "clear sky", "icon": "01n"}], "clouds": {"all": 0}, "wind": {"speed": 0.97, "deg": 143.5}, "snow": {}, "sys": {"pod": "n"}, "dt_txt": "2019-01-15 15:00:00"}, {"dt": 1547575200, "main": {"temp": -32.38, "temp_min": -32.38, "temp_max": -32.38, "pressure": 801.49, "sea_level": 1054.08, "grnd_level": 801.49, "humidity": 32, "temp_kf": 0}, "weather": [{"id": 800, "main": "Clear", "description": "clear sky", "icon": "01n"}], "clouds": {"all": 0}, "wind": {"speed": 0.98, "deg": 140.502}, "snow": {}, "sys": {"pod": "n"}, "dt_txt": "2019-01-15 18:00:00"}, {"dt": 1547586000, "main": {"temp": -33.17, "temp_min": -33.17, "temp_max": -33.17, "pressure": 801.29, "sea_level": 1054.31, "grnd_level": 801.29, "humidity": 34, "temp_kf": 0}, "weather": [{"id": 800, "main": "Clear", "description": "clear sky", "icon": "01n"}], "clouds": {"all": 0}, "wind": {"speed": 0.94, "deg": 143.003}, "snow": {}, "sys": {"pod": "n"}, "dt_txt": "2019-01-15 21:00:00"}], "city": {"id": 1488048, "name": "Ulagan", "coord": {"lat": 50.6321, "lon": 87.9563}, "country": "RU", "population": 2623}}