{"cod": "200", "message": 0.0032, "cnt": 39, "list": [{"dt": 1547175600, "main": {"temp": -34.77, "temp_min": -36.09, "temp_max": -34.77, "pressure": 1019.8, "sea_level": 1029.45, "grnd_level": 1019.8, "humidity": 0, "temp_kf": 1.32}, "weather": [{"id": 600, "main": "Snow", "description": "light snow", "icon": "13d"}], "clouds": {"all": 68}, "wind": {"speed": 2.56, "deg": 142.502}, "snow": {"3h": 0.063}, "sys": {"pod": "d"}, "dt_txt": "2019-01-11 03:00:00"}, {"dt": 1547186400, "main": {"temp": -33.6, "temp_min": -34.6, "temp_max": -33.6, "pressure": 1020.17, "sea_level": 1029.7, "grnd_level": 1020.17, "humidity": 50, "temp_kf": 0.99}, "weather": [{"id": 600, "main": "Snow", "description": "light snow", "icon": "13n"}], "clouds": {"all": 48}, "wind": {"speed": 2.77, "deg": 141.504}, "snow": {"3h": 0.107}, "sys": {"pod": "n"}, "dt_txt": "2019-01-11 06:00:00"}, {"dt": 1547197200, "main": {"temp": -33.01, "temp_min": -33.67, "temp_max": -33.01, "pressure": 1020.98, "sea_level": 1030.56, "grnd_level": 1020.98, "humidity": 46, "temp_kf": 0.66}, "weather": [{"id": 600, "main": "Snow", "description": "light snow", "icon": "13n"}], "clouds": {"all": 56}, "wind": {"speed": 3.31, "deg": 148.004}, "snow": {"3h": 0.117}, "sys": {"pod": "n"}, "dt_txt": "2019-01-11 09:00:00"}, {"dt": 1547208000, "main": {"temp": -32.48, "temp_min": -32.82, "temp_max": -32.48, "pressure": 1022.14, "sea_level": 1031.72, "grnd_level": 1022.14, "humidity": 42, "temp_kf": 0.33}, "weather": [{"id": 600, "main": "Snow", "description": "light snow", "icon": "13n"}], "clouds": {"all": 48}, "wind": {"speed": 3.47, "deg": 152.501}, "snow": {"3h": 0.118}, "sys": {"pod": "n"}, "dt_txt": "2019-01-11 12:00:00"}, {"dt": 1547218800, "main": {"temp": -32.21, "temp_min": -32.21, "temp_max": -32.21, "pressure": 1023.44, "sea_level": 1033.02, "grnd_level": 1023.44, "humidity": 40, "temp_kf": 0}, "weather": [{"id": 600, "main": "Snow", "description": "light snow", "icon": "13n"}], "clouds": {"all": 56}, "wind": {"speed": 3.6, "deg": 159.003}, "snow": {"3h": 0.1195}, "sys": {"pod": "n"}, "dt_txt": "2019-01-11 15:00:00"}, {"dt": 1547229600, "main": {"temp": -31.8, "temp_min": -31.8, "temp_max": -31.8, "pressure": 1025.32, "sea_level": 1034.86, "grnd_level": 1025.32, "humidity": 38, "temp_kf": 0}, "weather": [{"id": 600, "main": "Snow", "description": "light snow", "icon": "13n"}], "clouds": {"all": 48}, "wind": {"speed": 3.66, "deg": 161}, "snow": {"3h": 0.075}, "sys": {"pod": "n"}, "dt_txt": "2019-01-11 18:00:00"}, {"dt": 1547240400, "main": {"temp": -31.53, "temp_min": -31.53, "temp_max": -31.53, "pressure": 1027.11, "sea_level": 1036.64, "grnd_level": 1027.11, "humidity": 75, "temp_kf": 0}, "weather": [{"id": 600, "main": "Snow", "description": "light snow", "icon": "13n"}], "clouds": {"all": 48}, "wind": {"speed": 3.76, "deg": 162}, "snow": {"3h": 0.0425}, "sys": {"pod": "n"}, "dt_txt": "2019-01-11 21:00:00"}, {"dt": 1547251200, "main": {"temp": -31.16, "temp_min": -31.16, "temp_max": -31.16, "pressure": 1029.3, "sea_level": 1038.84, "grnd_level": 1029.3, "humidity": 72, "temp_kf": 0}, "weather": [{"id": 600, "main": "Snow", "description": "light snow", "icon": "13n"}], "clouds": {"all": 44}, "wind": {"speed": 3.91, "deg": 161.001}, "snow": {"3h": 0.04875}, "sys": {"pod": "n"}, "dt_txt": "2019-01-12 00:00:00"}, {"dt": 1547262000, "main": {"temp": -30.7, "temp_min": -30.7, "temp_max": -30.7, "pressure": 1031, "sea_level": 1040.66, "grnd_level": 1031, "humidity": 69, "temp_kf": 0}, "weather": [{"id": 600, "main": "Snow", "description": "light snow", "icon": "13d"}], "clouds": {"all": 32}, "wind": {"speed": 4.01, "deg": 161.502}, "snow": {"3h": 0.0475}, "sys": {"pod": "d"}, "dt_txt": "2019-01-12 03:00:00"}, {"dt": 1547272800, "main": {"temp": -30.56, "temp_min": -30.56, "temp_max": -30.56, "pressure": 1033, "sea_level": 1042.65, "grnd_level": 1033, "humidity": 34, "temp_kf": 0}, "weather": [{"id": 800, "main": "Clear", "description": "clear sky", "icon": "01n"}], "clouds": {"all": 36}, "wind": {"speed": 3.75, "deg": 160.5}, "snow": {"3h": 0.02125}, "sys": {"pod": "n"}, "dt_txt": "2019-01-12 06:00:00"}, {"dt": 1547283600, "main": {"temp": -30.4, "temp_min": -30.4, "temp_max": -30.4, "pressure": 1035.12, "sea_level": 1044.72, "grnd_level": 1035.12, "humidity": 68, "temp_kf": 0}, "weather": [{"id": 600, "main": "Snow", "description": "light snow", "icon": "13n"}], "clouds": {"all": 44}, "wind": {"speed": 4.02, "deg": 163.001}, "snow": {"3h": 0.03125}, "sys": {"pod": "n"}, "dt_txt": "2019-01-12 09:00:00"}, {"dt": 1547294400, "main": {"temp": -31.19, "temp_min": -31.19, "temp_max": -31.19, "pressure": 1036.77, "sea_level": 1046.43, "grnd_level": 1036.77, "humidity": 37, "temp_kf": 0}, "weather": [{"id": 800, "main": "Clear", "description": "clear sky", "icon": "01n"}], "clouds": {"all": 24}, "wind": {"speed": 3.51, "deg": 167.502}, "snow": {"3h": 0.015}, "sys": {"pod": "n"}, "dt_txt": "2019-01-12 12:00:00"}, {"dt": 1547305200, "main": {"temp": -32.77, "temp_min": -32.77, "temp_max": -32.77, "pressure": 1038.32, "sea_level": 1048, "grnd_level": 1038.32, "humidity": 43, "temp_kf": 0}, "weather": [{"id": 800, "main": "Clear", "description": "clear sky", "icon": "01n"}], "clouds": {"all": 12}, "wind": {"speed": 3.27, "deg": 154.5}, "snow": {"3h": 0.00125}, "sys": {"pod": "n"}, "dt_txt": "2019-01-12 15:00:00"}, {"dt": 1547316000, "main": {"temp": -33.21, "temp_min": -33.21, "temp_max": -33.21, "pressure": 1039.17, "sea_level": 1048.95, "grnd_level": 1039.17, "humidity": 45, "temp_kf": 0}, "weather": [{"id": 800, "main": "Clear", "description": "clear sky", "icon": "01n"}], "clouds": {"all": 24}, "wind": {"speed": 3.21, "deg": 144.501}, "snow": {"3h": 0.0025000000000001}, "sys": {"pod": "n"}, "dt_txt": "2019-01-12 18:00:00"}, {"dt": 1547326800, "main": {"temp": -32.4, "temp_min": -32.4, "temp_max": -32.4, "pressure": 1039.14, "sea_level": 1048.79, "grnd_level": 1039.14, "humidity": 41, "temp_kf": 0}, "weather": [{"id": 800, "main": "Clear", "description": "clear sky", "icon": "01n"}], "clouds": {"all": 32}, "wind": {"speed": 3.24, "deg": 147.502}, "snow": {"3h": 0.0175}, "sys": {"pod": "n"}, "dt_txt": "2019-01-12 21:00:00"}, {"dt": 1547337600, "main": {"temp": -31.22, "temp_min": -31.22, "temp_max": -31.22, "pressure": 1039.06, "sea_level": 1048.77, "grnd_level": 1039.06, "humidity": 73, "temp_kf": 0}, "weather": [{"id": 600, "main": "Snow", "description": "light snow", "icon": "13n"}], "clouds": {"all": 36}, "wind": {"speed": 3.19, "deg": 156.502}, "snow": {"3h": 0.0425}, "sys": {"pod": "n"}, "dt_txt": "2019-01-13 00:00:00"}, {"dt": 1547348400, "main": {"temp": -30.13, "temp_min": -30.13, "temp_max": -30.13, "pressure": 1038.88, "sea_level": 1048.56, "grnd_level": 1038.88, "humidity": 33, "temp_kf": 0}, "weather": [{"id": 600, "main": "Snow", "description": "light snow", "icon": "13d"}], "clouds": {"all": 32}, "wind": {"speed": 3.03, "deg": 159.502}, "snow": {"3h": 0.0325}, "sys": {"pod": "d"}, "dt_txt": "2019-01-13 03:00:00"}, {"dt": 1547359200, "main": {"temp": -31.27, "temp_min": -31.27, "temp_max": -31.27, "pressure": 1038.24, "sea_level": 1047.9, "grnd_level": 1038.24, "humidity": 37, "temp_kf": 0}, "weather": [{"id": 800, "main": "Clear", "description": "clear sky", "icon": "01n"}], "clouds": {"all": 20}, "wind": {"speed": 2.46, "deg": 148.501}, "snow": {"3h": 0.0075000000000001}, "sys": {"pod": "n"}, "dt_txt": "2019-01-13 06:00:00"}, {"dt": 1547370000, "main": {"temp": -31.96, "temp_min": -31.96, "temp_max": -31.96, "pressure": 1037.77, "sea_level": 1047.43, "grnd_level": 1037.77, "humidity": 39, "temp_kf": 0}, "weather": [{"id": 800, "main": "Clear", "description": "clear sky", "icon": "01n"}], "clouds": {"all": 32}, "wind": {"speed": 2.17, "deg": 141.5}, "snow": {"3h": 0.0075000000000001}, "sys": {"pod": "n"}, "dt_txt": "2019-01-13 09:00:00"}, {"dt": 1547380800, "main": {"temp": -32.11, "temp_min": -32.11, "temp_max": -32.11, "pressure": 1037.22, "sea_level": 1046.88, "grnd_level": 1037.22, "humidity": 40, "temp_kf": 0}, "weather": [{"id": 800, "main": "Clear", "description": "clear sky", "icon": "01n"}], "clouds": {"all": 44}, "wind": {"speed": 1.6, "deg": 155.001}, "snow": {"3h": 0.0125}, "sys": {"pod": "n"}, "dt_txt": "2019-01-13 12:00:00"}, {"dt": 1547391600, "main": {"temp": -32.35, "temp_min": -32.35, "temp_max": -32.35, "pressure": 1036.34, "sea_level": 1046.1, "grnd_level": 1036.34, "humidity": 41, "temp_kf": 0}, "weather": [{"id": 800, "main": "Clear", "description": "clear sky", "icon": "01n"}], "clouds": {"all": 44}, "wind": {"speed": 1.38, "deg": 138.5}, "snow": {"3h": 0.0125}, "sys": {"pod": "n"}, "dt_txt": "2019-01-13 15:00:00"}, {"dt": 1547402400, "main": {"temp": -32.66, "temp_min": -32.66, "temp_max": -32.66, "pressure": 1035.66, "sea_level": 1045.32, "grnd_level": 1035.66, "humidity": 42, "temp_kf": 0}, "weather": [{"id": 800, "main": "Clear", "description": "clear sky", "icon": "01n"}], "clouds": {"all": 44}, "wind": {"speed": 1.59, "deg": 143.501}, "snow": {"3h": 0.0075000000000001}, "sys": {"pod": "n"}, "dt_txt": "2019-01-13 18:00:00"}, {"dt": 1547413200, "main": {"temp": -33.12, "temp_min": -33.12, "temp_max": -33.12, "pressure": 1034.87, "sea_level": 1044.59, "grnd_level": 1034.87, "humidity": 44, "temp_kf": 0}, "weather": [{"id": 800, "main": "Clear", "description": "clear sky", "icon": "01n"}], "clouds": {"all": 44}, "wind": {"speed": 1.16, "deg": 145.502}, "snow": {"3h": 0.015}, "sys": {"pod": "n"}, "dt_txt": "2019-01-13 21:00:00"}, {"dt": 1547424000, "main": {"temp": -33.28, "temp_min": -33.28, "temp_max": -33.28, "pressure": 1034.63, "sea_level": 1044.41, "grnd_level": 1034.63, "humidity": 45, "temp_kf": 0}, "weather": [{"id": 800, "main": "Clear", "description": "clear sky", "icon": "01n"}], "clouds": {"all": 36}, "wind": {"speed": 1.36, "deg": 157.505}, "snow": {"3h": 0.0275}, "sys": {"pod": "n"}, "dt_txt": "2019-01-14 00:00:00"}, {"dt": 1547434800, "main": {"temp": -33.15, "temp_min": -33.15, "temp_max": -33.15, "pressure": 1034.29, "sea_level": 1044.04, "grnd_level": 1034.29, "humidity": 44, "temp_kf": 0}, "weather": [{"id": 600, "main": "Snow", "description": "light snow", "icon": "13d"}], "clouds": {"all": 36}, "wind": {"speed": 1.31, "deg": 166}, "snow": {"3h": 0.04}, "sys": {"pod": "d"}, "dt_txt": "2019-01-14 03:00:00"}, {"dt": 1547445600, "main": {"temp": -33.02, "temp_min": -33.02, "temp_max": -33.02, "pressure": 1034.07, "sea_level": 1043.79, "grnd_level": 1034.07, "humidity": 43, "temp_kf": 0}, "weather": [{"id": 800, "main": "Clear", "description": "clear sky", "icon": "01n"}], "clouds": {"all": 36}, "wind": {"speed": 1.93, "deg": 150.507}, "snow": {"3h": 0.02}, "sys": {"pod": "n"}, "dt_txt": "2019-01-14 06:00:00"}, {"dt": 1547456400, "main": {"temp": -33.69, "temp_min": -33.69, "temp_max": -33.69, "pressure": 1034.19, "sea_level": 1043.93, "grnd_level": 1034.19, "humidity": 46, "temp_kf": 0}, "weather": [{"id": 800, "main": "Clear", "description": "clear sky", "icon": "01n"}], "clouds": {"all": 24}, "wind": {"speed": 2.46, "deg": 151.003}, "snow": {"3h": 0.0125}, "sys": {"pod": "n"}, "dt_txt": "2019-01-14 09:00:00"}, {"dt": 1547467200, "main": {"temp": -33.62, "temp_min": -33.62, "temp_max": -33.62, "pressure": 1034.02, "sea_level": 1043.75, "grnd_level": 1034.02, "humidity": 46, "temp_kf": 0}, "weather": [{"id": 600, "main": "Snow", "description": "light snow", "icon": "13n"}], "clouds": {"all": 24}, "wind": {"speed": 2.62, "deg": 158.003}, "snow": {"3h": 0.0475}, "sys": {"pod": "n"}, "dt_txt": "2019-01-14 12:00:00"}, {"dt": 1547478000, "main": {"temp": -33.9, "temp_min": -33.9, "temp_max": -33.9, "pressure": 1033.74, "sea_level": 1043.47, "grnd_level": 1033.74, "humidity": 47, "temp_kf": 0}, "weather": [{"id": 600, "main": "Snow", "description": "light snow", "icon": "13n"}], "clouds": {"all": 32}, "wind": {"speed": 2.87, "deg": 159}, "snow": {"3h": 0.065}, "sys": {"pod": "n"}, "dt_txt": "2019-01-14 15:00:00"}, {"dt": 1547488800, "main": {"temp": -34.08, "temp_min": -34.08, "temp_max": -34.08, "pressure": 1033.55, "sea_level": 1043.17, "grnd_level": 1033.55, "humidity": 48, "temp_kf": 0}, "weather": [{"id": 600, "main": "Snow", "description": "light snow", "icon": "13n"}], "clouds": {"all": 32}, "wind": {"speed": 2.96, "deg": 156.502}, "snow": {"3h": 0.0475}, "sys": {"pod": "n"}, "dt_txt": "2019-01-14 18:00:00"}, {"dt": 1547499600, "main": {"temp": -33.79, "temp_min": -33.79, "temp_max": -33.79, "pressure": 1032.8, "sea_level": 1042.48, "grnd_level": 1032.8, "humidity": 47, "temp_kf": 0}, "weather": [{"id": 600, "main": "Snow", "description": "light snow", "icon": "13n"}], "clouds": {"all": 32}, "wind": {"speed": 2.76, "deg": 142.501}, "snow": {"3h": 0.0525}, "sys": {"pod": "n"}, "dt_txt": "2019-01-14 21:00:00"}, {"dt": 1547510400, "main": {"temp": -33.13, "temp_min": -33.13, "temp_max": -33.13, "pressure": 1032.05, "sea_level": 1041.8, "grnd_level": 1032.05, "humidity": 44, "temp_kf": 0}, "weather": [{"id": 600, "main": "Snow", "description": "light snow", "icon": "13n"}], "clouds": {"all": 32}, "wind": {"speed": 2.77, "deg": 140.502}, "snow": {"3h": 0.0525}, "sys": {"pod": "n"}, "dt_txt": "2019-01-15 00:00:00"}, {"dt": 1547521200, "main": {"temp": -32.37, "temp_min": -32.37, "temp_max": -32.37, "pressure": 1031.03, "sea_level": 1040.69, "grnd_level": 1031.03, "humidity": 41, "temp_kf": 0}, "weather": [{"id": 600, "main": "Snow", "description": "light snow", "icon": "13d"}], "clouds": {"all": 24}, "wind": {"speed": 2.81, "deg": 144.001}, "snow": {"3h": 0.05}, "sys": {"pod": "d"}, "dt_txt": "2019-01-15 03:00:00"}, {"dt": 1547532000, "main": {"temp": -31.97, "temp_min": -31.97, "temp_max": -31.97, "pressure": 1029.81, "sea_level": 1039.35, "grnd_level": 1029.81, "humidity": 39, "temp_kf": 0}, "weather": [{"id": 600, "main": "Snow", "description": "light snow", "icon": "13n"}], "clouds": {"all": 24}, "wind": {"speed": 2.97, "deg": 145.5}, "snow": {"3h": 0.035}, "sys": {"pod": "n"}, "dt_txt": "2019-01-15 06:00:00"}, {"dt": 1547542800, "main": {"temp": -31.99, "temp_min": -31.99, "temp_max": -31.99, "pressure": 1028.87, "sea_level": 1038.44, "grnd_level": 1028.87, "humidity": 39, "temp_kf": 0}, "weather": [{"id": 800, "main": "Clear", "description": "clear sky", "icon": "01n"}], "clouds": {"all": 24}, "wind": {"speed": 3.07, "deg": 151.5}, "snow": {"3h": 0.02}, "sys": {"pod": "n"}, "dt_txt": "2019-01-15 09:00:00"}, {"dt": 1547553600, "main": {"temp": -31.96, "temp_min": -31.96, "temp_max": -31.96, "pressure": 1027.72, "sea_level": 1037.25, "grnd_level": 1027.72, "humidity": 39, "temp_kf": 0}, "weather": [{"id": 600, "main": "Snow", "description": "light snow", "icon": "13n"}], "clouds": {"all": 32}, "wind": {"speed": 3.13, "deg": 151.001}, "snow": {"3h": 0.03}, "sys": {"pod": "n"}, "dt_txt": "2019-01-15 12:00:00"}, {"dt": 1547564400, "main": {"temp": -31.67, "temp_min": -31.67, "temp_max": -31.67, "pressure": 1026.15, "sea_level": 1035.64, "grnd_level": 1026.15, "humidity": 76, "temp_kf": 0}, "weather": [{"id": 800, "main": "Clear", "description": "clear sky", "icon": "01n"}], "clouds": {"all": 32}, "wind": {"speed": 3.42, "deg": 147.5}, "snow": {"3h": 0.025}, "sys": {"pod": "n"}, "dt_txt": "2019-01-15 15:00:00"}, {"dt": 1547575200, "main": {"temp": -31.1, "temp_min": -31.1, "temp_max": -31.1, "pressure": 1024.41, "sea_level": 1033.94, "grnd_level": 1024.41, "humidity": 36, "temp_kf": 0}, "weather": [{"id": 600, "main": "Snow", "description": "light snow", "icon": "13n"}], "clouds": {"all": 32}, "wind": {"speed": 3.45, "deg": 142.002}, "snow": {"3h": 0.035}, "sys": {"pod": "n"}, "dt_txt": "2019-01-15 18:00:00"}, {"dt": 1547586000, "main": {"temp": -30.4, "temp_min": -30.4, "temp_max": -30.4, "pressure": 1023.08, "sea_level": 1032.58, "grnd_level": 1023.08, "humidity": 67, "temp_kf": 0}, "weather": [{"id": 600, "main": "Snow", "description": "light snow", "icon": "13n"}], "clouds": {"all": 48}, "wind": {"speed": 3.37, "deg": 136.503}, "snow": {"3h": 0.065}, "sys": {"pod": "n"}, "dt_txt": "2019-01-15 21:00:00"}], "city": {"id": 2012530, "name": "Zhigansk", "coord": {"lat": 66.7656, "lon": 123.3741}, "country": "RU", "population": 3237}}